Workbook

Sheet Summary
B1: Home Depot (NYSE: HD)
B2: Summary Income Statement & Supporting Financials
B5: Period End: | C5: =DATE(2021,1,31) -> 44227 | D5: =DATE(2022,1,30) -> 44591 | E5: =DATE(2022,1,29) -> 44590 | F5: =DATE(2024,1,28) -> 45319
B6: USD millions (expect per share data) | C6: FY2021A | D6: FY2022A | E6: FY2023A | F6: FY2024A | G6: FY2025E | H6: FY2026E | I6: FY2027E | J6: FY2028E | K6: FY2029E | L6: FY2030E | M6: FY2031E
C9: Historical | G9: Projections
B10: Income Statement
B11: Revenue | C11: 132110 | D11: 151157 | E11: 157403 | F11: 152669 | G11: ='Annual Model'!G10 -> 154195.69 | H11: ='Annual Model'!H10 -> 158821.56 | I11: ='Annual Model'!I10 -> 165174.42 | J11: ='Annual Model'!J10 -> 172276.92 | K11: ='Annual Model'!K10 -> 179168 | L11: ='Annual Model'!L10 -> 185886.8 | M11: ='Annual Model'!M10 -> 192392.84
B12: Growth % | D12: =D11/C11-1 -> 0.14417531 | E12: =E11/D11-1 -> 0.041321275 | F12: =F11/E11-1 -> -0.030075666 | G12: =G11/F11-1 -> 0.01 | H12: =H11/G11-1 -> 0.03 | I12: =I11/H11-1 -> 0.04 | J12: =J11/I11-1 -> 0.043 | K12: =K11/J11-1 -> 0.04 | ... M12: =M11/L11-1 -> 0.035
B13: COGS | C13: ='Annual Model'!C11 -> 87257 | D13: ='Annual Model'!D11 -> 100325 | E13: ='Annual Model'!E11 -> 104625 | F13: ='Annual Model'!F11 -> 101709 | G13: ='Annual Model'!G11 -> 102848.53 | H13: ='Annual Model'!H11 -> 106092.8 | I13: ='Annual Model'!I11 -> 110501.69 | J13: ='Annual Model'!J11 -> 115425.54 | ... M13: ='Annual Model'!M11 -> 129480.38
B14: COGS % Rev | D14: =D13/D11 -> 0.66371389 | E14: =E13/E11 -> 0.66469508 | F14: =F13/F11 -> 0.66620598 | G14: =G13/G11 -> 0.667 | H14: =H13/H11 -> 0.668 | I14: =I13/I11 -> 0.669 | J14: =J13/J11 -> 0.67 | K14: =K13/K11 -> 0.671 | ... M14: =M13/M11 -> 0.673
B15: COGS Growth % | G15: =G14/F14-1 -> 0.0011918611 | H15: =H14/G14-1 -> 0.0014992504 | I15: =I14/H14-1 -> 0.001497006 | J15: =J14/I14-1 -> 0.0014947683 | K15: =K14/J14-1 -> 0.0014925373 | L15: =L14/K14-1 -> 0.001490313 | M15: =M14/L14-1 -> 0.0014880952
B16: Gross Profit | C16: ='Annual Model'!C12 -> 44853 | D16: ='Annual Model'!D12 -> 50832 | E16: ='Annual Model'!E12 -> 52778 | F16: ='Annual Model'!F12 -> 50960 | G16: ='Annual Model'!G12 -> 51347.165 | H16: ='Annual Model'!H12 -> 52728.758 | I16: ='Annual Model'!I12 -> 54672.734 | J16: ='Annual Model'!J12 -> 56851.385 | ... M16: ='Annual Model'!M12 -> 62912.458
B17: Gross Margin % | D17: ='Annual Model'!D12/'Annual Model'!D10 -> 0.33628611 | E17: ='Annual Model'!E12/'Annual Model'!E10 -> 0.33530492 | F17: ='Annual Model'!F12/'Annual Model'!F10 -> 0.33379402 | G17: ='Annual Model'!G12/'Annual Model'!G10 -> 0.333 | H17: ='Annual Model'!H12/'Annual Model'!H10 -> 0.332 | I17: ='Annual Model'!I12/'Annual Model'!I10 -> 0.331 | J17: ='Annual Model'!J12/'Annual Model'!J10 -> 0.33 | K17: ='Annual Model'!K12/'Annual Model'!K10 -> 0.329 | ... M17: ='Annual Model'!M12/'Annual Model'!M10 -> 0.327
B18: EBITDA | C18: ='Annual Model'!C15 -> 20406 | D18: ='Annual Model'!D15 -> 25426 | E18: ='Annual Model'!E15 -> 26494 | F18: ='Annual Model'!F15 -> 24362 | G18: ='Annual Model'!G15 -> 24581.389 | H18: ='Annual Model'!H15 -> 25160.009 | I18: ='Annual Model'!I15 -> 26001.235 | J18: ='Annual Model'!J15 -> 26947.011 | ... M18: ='Annual Model'!M15 -> 29516.3
B19: YoY Growth % | D19: =D18/C18-1 -> 0.24600608 | E19: =E18/D18-1 -> 0.042004248 | F19: =F18/E18-1 -> -0.08047105 | G19: =G18/F18-1 -> 0.0090053669 | H19: =H18/G18-1 -> 0.023538951 | I19: =I18/H18-1 -> 0.033435041 | J19: =J18/I18-1 -> 0.036374279 | K19: =K18/J18-1 -> 0.033351099 | ... M19: =M18/L18-1 -> 0.028297363
B20: EBITDA Margin % | D20: ='Annual Model'!D15/'Annual Model'!D10 -> 0.16820921 | E20: ='Annual Model'!E15/'Annual Model'!E10 -> 0.16831954 | F20: ='Annual Model'!F15/'Annual Model'!F10 -> 0.15957398 | G20: ='Annual Model'!G15/'Annual Model'!G10 -> 0.15941683 | H20: ='Annual Model'!H15/'Annual Model'!H10 -> 0.15841683 | I20: ='Annual Model'!I15/'Annual Model'!I10 -> 0.15741683 | J20: ='Annual Model'!J15/'Annual Model'!J10 -> 0.15641683 | K20: ='Annual Model'!K15/'Annual Model'!K10 -> 0.15541683 | ... M20: ='Annual Model'!M15/'Annual Model'!M10 -> 0.15341683
B21: EBIT | C21: ='Annual Model'!C17 -> 18278 | D21: ='Annual Model'!D17 -> 23040 | E21: ='Annual Model'!E17 -> 24039 | F21: ='Annual Model'!F17 -> 21689 | G21: ='Annual Model'!G17 -> 22075.783 | H21: ='Annual Model'!H17 -> 22579.235 | I21: ='Annual Model'!I17 -> 23317.23 | J21: ='Annual Model'!J17 -> 24147.594 | ... M21: ='Annual Model'!M17 -> 26390.009
B22: Operating Margin % | C22: =C21/C11 -> 0.1383544 | D22: =D21/D11 -> 0.1524243 | E22: =E21/E11 -> 0.15272263 | F22: =F21/F11 -> 0.14206551 | G22: =G21/G11 -> 0.14316732 | H22: =H21/H11 -> 0.14216732 | I22: =I21/I11 -> 0.14116732 | J22: =J21/J11 -> 0.14016732 | ... M22: =M21/M11 -> 0.13716732
B23: Growth Rate % | D23: =D21/C21-1 -> 0.26053179 | E23: =E21/D21-1 -> 0.043359375 | F23: =F21/E21-1 -> -0.09775781 | G23: =G21/F21-1 -> 0.017833141 | H23: =H21/G21-1 -> 0.022805621 | I23: =I21/H21-1 -> 0.032684676 | J23: =J21/I21-1 -> 0.035611604 | K23: =K21/J21-1 -> 0.032580296 | ... M23: =M21/L21-1 -> 0.027509082
B24: EBT | C24: ='Annual Model'!C22 -> 16978 | D24: ='Annual Model'!D22 -> 21737 | E24: ='Annual Model'!E22 -> 22477 | F24: ='Annual Model'!F22 -> 19924 | G24: ='Annual Model'!G22 -> 20001.935 | H24: ='Annual Model'!H22 -> 20620.25 | I24: ='Annual Model'!I22 -> 21489.355 | J24: ='Annual Model'!J22 -> 22451.436 | ... M24: ='Annual Model'!M22 -> 25104.254
B25: EBT Margin % | D25: ='Annual Model'!D22/'Annual Model'!D10 -> 0.14380412 | E25: ='Annual Model'!E22/'Annual Model'!E10 -> 0.14279906 | F25: ='Annual Model'!F22/'Annual Model'!F10 -> 0.13050456 | G25: ='Annual Model'!G22/'Annual Model'!G10 -> 0.12971786 | H25: ='Annual Model'!H22/'Annual Model'!H10 -> 0.12983281 | I25: ='Annual Model'!I22/'Annual Model'!I10 -> 0.13010098 | J25: ='Annual Model'!J22/'Annual Model'!J10 -> 0.13032179 | K25: ='Annual Model'!K22/'Annual Model'!K10 -> 0.1304255 | ... M25: ='Annual Model'!M22/'Annual Model'!M10 -> 0.13048435
B26: Net Earnings (Income) | C26: ='Annual Model'!C25 -> 12866 | D26: ='Annual Model'!D25 -> 16433 | E26: ='Annual Model'!E25 -> 17105 | F26: ='Annual Model'!F25 -> 15143 | G26: ='Annual Model'!G25 -> 15201.47 | H26: ='Annual Model'!H25 -> 15671.39 | I26: ='Annual Model'!I25 -> 16331.91 | J26: ='Annual Model'!J25 -> 17063.092 | ... M26: ='Annual Model'!M25 -> 19079.233
B27: Growth % | D27: =Summary!D26/Summary!C26-1 -> 0.27724234 | E27: =Summary!E26/Summary!D26-1 -> 0.040893324 | F27: =Summary!F26/Summary!E26-1 -> -0.1147033 | G27: =Summary!G26/Summary!F26-1 -> 0.0038612196 | H27: =Summary!H26/Summary!G26-1 -> 0.030912779 | I27: =Summary!I26/Summary!H26-1 -> 0.04214811 | J27: =Summary!J26/Summary!I26-1 -> 0.044770148 | K27: =Summary!K26/Summary!J26-1 -> 0.040827685 | ... M27: =Summary!M26/Summary!L26-1 -> 0.035062897

Sheet Assumptions
B1: Home Depot (NYSE: HD)
B2: Assumptions/Drivers
B5: Period End: | C5: =DATE(2021,1,31) -> 44227 | D5: =DATE(2022,1,30) -> 44591 | E5: =DATE(2022,1,29) -> 44590 | F5: =DATE(2024,1,28) -> 45319
B6: USD millions (expect per share data) | C6: FY2021A | D6: FY2022A | E6: FY2023A | F6: FY2024A | G6: FY2025E | H6: FY2026E | I6: FY2027E | J6: FY2028E | K6: FY2029E | L6: FY2030E | M6: FY2031E
B9: Income Statement
B10: Revenue growth % YoY | D10: ='Annual Model'!D10/'Annual Model'!C10-1 -> 0.14417531 | E10: ='Annual Model'!E10/'Annual Model'!D10-1 -> 0.041321275 | F10: ='Annual Model'!F10/'Annual Model'!E10-1 -> -0.030075666 | G10: 0.01 | H10: 0.03 | I10: 0.04 | J10: 0.043 | K10: 0.04 | L10: 0.0375 | M10: 0.035
B11: COGS % Rev | C11: ='Annual Model'!C11/'Annual Model'!C10 -> 0.66048747 | D11: ='Annual Model'!D11/'Annual Model'!D10 -> 0.66371389 | E11: ='Annual Model'!E11/'Annual Model'!E10 -> 0.66469508 | F11: ='Annual Model'!F11/'Annual Model'!F10 -> 0.66620598 | G11: 0.667 | H11: 0.668 | I11: 0.669 | J11: 0.67 | K11: 0.671 | L11: 0.672 | M11: 0.673
B12: SG&A % Rev | C12: ='Annual Model'!C14/'Annual Model'!C10 -> 0.18505034 | D12: ='Annual Model'!D14/'Annual Model'!D10 -> 0.1680769 | E12: ='Annual Model'!E14/'Annual Model'!E10 -> 0.16698538 | F12: ='Annual Model'!F14/'Annual Model'!F10 -> 0.17422004 | G12: =AVERAGE(C12:F12) -> 0.17358317 | H12: =G12 -> 0.17358317 | I12: =H12 -> 0.17358317 | J12: =I12 -> 0.17358317 | K12: =J12 -> 0.17358317 | L12: =K12 -> 0.17358317 | M12: =L12 -> 0.17358317
B13: Depreciation % Rev | C13: ='Annual Model'!C16/'Annual Model'!C10 -> 0.016107789 | D13: ='Annual Model'!D16/'Annual Model'!D10 -> 0.015784912 | E13: ='Annual Model'!E16/'Annual Model'!E10 -> 0.015596907 | F13: ='Annual Model'!F16/'Annual Model'!F10 -> 0.017508466 | G13: =AVERAGE(C13:F13) -> 0.016249519 | H13: =G13 -> 0.016249519 | I13: =H13 -> 0.016249519 | J13: =I13 -> 0.016249519 | K13: =J13 -> 0.016249519 | L13: =K13 -> 0.016249519 | M13: =L13 -> 0.016249519
B14: Income Tax Expense | C14: ='Annual Model'!C24 -> 0.24219578 | D14: ='Annual Model'!D24 -> 0.24400791 | E14: ='Annual Model'!E24 -> 0.23899987 | F14: ='Annual Model'!F24 -> 0.23996186 | G14: 0.24 | H14: 0.24 | I14: 0.24 | J14: 0.24 | K14: 0.24 | L14: 0.24 | M14: 0.24
B15: Basic Weighted Average Common Shares | C15: ='Annual Model'!C30 -> 1074 | D15: ='Annual Model'!D30 -> 1054 | E15: ='Annual Model'!E30 -> 1022 | F15: ='Annual Model'!F30 -> 999 | G15: 995 | H15: 992 | I15: 990 | J15: 988 | K15: 986 | L15: 986 | M15: 984
B16: Share Growth % | D16: =D15/C15-1 -> -0.018621974 | E16: =E15/D15-1 -> -0.030360531 | F16: =F15/E15-1 -> -0.022504892 | G16: =G15/F15-1 -> -0.004004004 | H16: =H15/G15-1 -> -0.0030150754 | I16: =I15/H15-1 -> -0.002016129 | J16: =J15/I15-1 -> -0.002020202 | K16: =K15/J15-1 -> -0.0020242915 | ... M16: =M15/L15-1 -> -0.0020283976
B17: Diluted Weighted Average Common Shares | C17: ='Annual Model'!C31 -> 1078 | D17: ='Annual Model'!D31 -> 1058 | E17: ='Annual Model'!E31 -> 1025 | F17: ='Annual Model'!F31 -> 1002 | G17: 997 | H17: 995 | I17: 992 | J17: 990 | K17: 988 | L17: 988 | M17: 986
B18: Share Growth % | D18: =D17/C17-1 -> -0.018552876 | E18: =E17/D17-1 -> -0.031190926 | F18: =F17/E17-1 -> -0.022439024 | G18: =G17/F17-1 -> -0.00499002 | H18: =H17/G17-1 -> -0.0020060181 | I18: =I17/H17-1 -> -0.0030150754 | J18: =J17/I17-1 -> -0.002016129 | K18: =K17/J17-1 -> -0.002020202 | ... M18: =M17/L17-1 -> -0.0020242915
B20: Balance Sheet
B21: Other Current Assets: | C21: ='Annual Model'!C41 -> 1040 | D21: ='Annual Model'!D41 -> 963 | E21: ='Annual Model'!E41 -> 1218 | F21: ='Annual Model'!F41 -> 1511 | G21: 1511 | H21: 1511 | I21: 1511 | J21: 1511 | K21: 1511 | L21: 1511 | M21: 1511
B22: Operating Lease ROU Assets | C22: ='Annual Model'!C45 -> 5595 | D22: ='Annual Model'!D45 -> 5962 | E22: ='Annual Model'!E45 -> 5968 | F22: ='Annual Model'!F45 -> 6941 | G22: 6941 | H22: 6941 | I22: 6941 | J22: 6941 | K22: 6941 | L22: 6941 | M22: 6941
B23: Goodwill | C23: ='Annual Model'!C46 -> 2254 | D23: ='Annual Model'!D46 -> 7126 | E23: ='Annual Model'!E46 -> 7449 | F23: ='Annual Model'!F46 -> 7444 | G23: 7444 | H23: 7444 | I23: 7444 | J23: 7444 | K23: 7444 | L23: 7444 | M23: 7444
B25: Cash Flow Statement
B26: CAPEX % Rev | C26: =-'Annual Model'!C108/'Annual Model'!C10 -> 0.018643555 | D26: =-'Annual Model'!D108/'Annual Model'!D10 -> 0.016975727 | E26: =-'Annual Model'!E108/'Annual Model'!E10 -> 0.019815378 | F26: =-'Annual Model'!F108/'Annual Model'!F10 -> 0.021130681 | G26: 0.02 | H26: 0.02 | I26: 0.02 | J26: 0.02 | K26: 0.02 | L26: 0.02 | M26: 0.02
B27: Intangible Asset Amortization: | C27: ='Annual Model'!C89 -> 0 | D27: ='Annual Model'!D89 -> 0 | E27: ='Annual Model'!E89 -> 0 | F27: ='Annual Model'!F89 -> 0 | G27: 0 | H27: 0 | I27: 0 | J27: 0 | K27: 0 | L27: 0 | M27: 0
B28: Stock-Based Compensation Expense: | C28: ='Annual Model'!C90 -> 310 | D28: ='Annual Model'!D90 -> 399 | E28: ='Annual Model'!E90 -> 366 | F28: ='Annual Model'!F90 -> 380 | G28: =G29*'Annual Model'!G10 -> 385.48923 | H28: =H29*'Annual Model'!H10 -> 397.0539 | I28: =I29*'Annual Model'!I10 -> 412.93606 | J28: =J29*'Annual Model'!J10 -> 430.69231 | K28: =K29*'Annual Model'!K10 -> 447.92 | L28: =L29*'Annual Model'!L10 -> 464.717 | M28: =M29*'Annual Model'!M10 -> 480.9821
B29: SBC % Rev | C29: ='Annual Model'!C90/'Annual Model'!C10 -> 0.0023465294 | D29: ='Annual Model'!D90/'Annual Model'!D10 -> 0.0026396396 | E29: ='Annual Model'!E90/'Annual Model'!E10 -> 0.0023252416 | F29: ='Annual Model'!F90/'Annual Model'!F10 -> 0.0024890449 | G29: 0.0025 | H29: 0.0025 | I29: 0.0025 | J29: 0.0025 | K29: 0.0025 | L29: 0.0025 | M29: 0.0025
B30: Impairment Loss: | C30: ='Annual Model'!C91 -> 0 | D30: ='Annual Model'!D91 -> 0 | E30: ='Annual Model'!E91 -> 0 | F30: ='Annual Model'!F91 -> 0 | G30: 0 | H30: 0 | I30: 0 | J30: 0 | K30: 0 | L30: 0 | M30: 0
B31: Changes in Other Current Assets: | C31: ='Annual Model'!C94 -> 43 | D31: ='Annual Model'!D94 -> -330 | E31: ='Annual Model'!E94 -> -311 | F31: ='Annual Model'!F94 -> -184 | G31: -184 | H31: -184 | I31: -184 | J31: -184 | K31: -184 | L31: -184 | M31: -184
B32: Changes in Deferred Revenue: | C32: ='Annual Model'!C92 -> 702 | D32: ='Annual Model'!D92 -> 775 | E32: ='Annual Model'!E92 -> -526 | F32: ='Annual Model'!F92 -> -318 | G32: =G33*'Annual Model'!G10 -> 231.29354 | H32: =H33*'Annual Model'!H10 -> 238.23234 | I32: =I33*'Annual Model'!I10 -> 247.76163 | J32: =J33*'Annual Model'!J10 -> 258.41538 | K32: =K33*'Annual Model'!K10 -> 268.752 | L32: =L33*'Annual Model'!L10 -> 278.8302 | M32: =M33*'Annual Model'!M10 -> 288.58926
B33: DR % Rev | C33: ='Annual Model'!C92/'Annual Model'!C10 -> 0.0053137537 | D33: ='Annual Model'!D92/'Annual Model'!D10 -> 0.0051271195 | E33: ='Annual Model'!E92/'Annual Model'!E10 -> -0.0033417406 | F33: ='Annual Model'!F92/'Annual Model'!F10 -> -0.0020829376 | G33: 0.0015 | H33: 0.0015 | I33: 0.0015 | J33: 0.0015 | K33: 0.0015 | L33: 0.0015 | M33: 0.0015
B34: Other Operating Activities: | C34: ='Annual Model'!C95 -> 121 | D34: ='Annual Model'!D95 -> 196 | E34: ='Annual Model'!E95 -> 271 | F34: ='Annual Model'!F95 -> 314 | G34: =G35*'Annual Model'!G10 -> 354.65009 | H34: =H35*'Annual Model'!H10 -> 397.0539 | I34: =I35*'Annual Model'!I10 -> 445.97094 | J34: =J35*'Annual Model'!J10 -> 499.60308 | K34: =K35*'Annual Model'!K10 -> 555.4208 | L34: =L35*'Annual Model'!L10 -> 613.42644 | M34: =M35*'Annual Model'!M10 -> 673.37493
B35: Other Operating Activities % Rev | C35: ='Annual Model'!C95/'Annual Model'!C10 -> 0.00091590341 | D35: ='Annual Model'!D95/'Annual Model'!D10 -> 0.0012966651 | E35: ='Annual Model'!E95/'Annual Model'!E10 -> 0.0017216953 | F35: ='Annual Model'!F95/'Annual Model'!F10 -> 0.0020567371 | G35: 0.0023 | H35: 0.0025 | I35: 0.0027 | J35: 0.0029 | K35: 0.0031 | L35: 0.0033 | M35: 0.0035
B37: Payments for Businesses Acquired: | C37: ='Annual Model'!C109 -> -7780 | D37: ='Annual Model'!D109 -> -421 | E37: ='Annual Model'!E109 -> 0 | F37: ='Annual Model'!F109 -> -1514 | G37: 0 | H37: 0 | I37: 0 | J37: 0 | K37: 0 | L37: 0 | M37: 0
B38: Proceeds from Sales of Property and Equipment: | C38: ='Annual Model'!C110 -> 0 | D38: ='Annual Model'!D110 -> 0 | E38: ='Annual Model'!E110 -> 0 | F38: ='Annual Model'!F110 -> 0 | G38: 0 | H38: 0 | I38: 0 | J38: 0 | K38: 0 | L38: 0 | M38: 0
B39: Other Investing Activities: | C39: ='Annual Model'!C111 -> 73 | D39: ='Annual Model'!D111 -> 18 | E39: ='Annual Model'!E111 -> -21 | F39: ='Annual Model'!F111 -> 11 | G39: 10 | H39: 10 | I39: 10 | J39: 10 | K39: 10 | L39: 10 | M39: 10
B41: Repurchases of Common Stock: | C41: ='Annual Model'!C122 -> -791 | D41: ='Annual Model'!D122 -> -14809 | E41: ='Annual Model'!E122 -> -6696 | F41: ='Annual Model'!F122 -> -7951 | G41: -3500 | H41: -3500 | I41: -3500 | J41: -3500 | K41: -3500 | L41: -3500 | M41: -3500
B42: Proceeds from Sales of Common Stock: | C42: ='Annual Model'!C123 -> 326 | D42: ='Annual Model'!D123 -> 337 | E42: ='Annual Model'!E123 -> 264 | F42: ='Annual Model'!F123 -> 323 | G42: =AVERAGE(C42:F42) -> 312.5 | H42: =G42 -> 312.5 | I42: =H42 -> 312.5 | J42: =I42 -> 312.5 | K42: =J42 -> 312.5 | L42: =K42 -> 312.5 | M42: =L42 -> 312.5
B43: Cash Dividends: | C43: ='Annual Model'!C124 -> -6451 | D43: ='Annual Model'!D124 -> -6985 | E43: ='Annual Model'!E124 -> -7789 | F43: ='Annual Model'!F124 -> -8383 | G43: =-G44*'Annual Model'!G30 -> -8955 | H43: =-H44*'Annual Model'!H30 -> -9076.8 | I43: =-I44*'Annual Model'!I30 -> -9207 | J43: =-J44*'Annual Model'!J30 -> -9336.6 | K43: =-K44*'Annual Model'!K30 -> -9367 | L43: =-L44*'Annual Model'!L30 -> -9416.3 | M43: =-M44*'Annual Model'!M30 -> -9446.4
B44: Price per Share | C44: =-C43/'Annual Model'!C30 -> 6.0065177 | D44: =-D43/'Annual Model'!D30 -> 6.6271347 | E44: =-E43/'Annual Model'!E30 -> 7.6213307 | F44: =-F43/'Annual Model'!F30 -> 8.3913914 | G44: 9 | H44: 9.15 | I44: 9.3 | J44: 9.45 | K44: 9.5 | L44: 9.55 | M44: 9.6
B45: Dividend Increase % | D45: =D44/C44-1 -> 0.10332393 | E45: =E44/D44-1 -> 0.15001898 | F45: =F44/E44-1 -> 0.10104019 | G45: =G44/F44-1 -> 0.072527735 | H45: =H44/G44-1 -> 0.016666667 | I45: =I44/H44-1 -> 0.016393443 | J45: =J44/I44-1 -> 0.016129032 | K45: =K44/J44-1 -> 0.0052910053 | ... M45: =M44/L44-1 -> 0.0052356021
B46: Other Financing Activities: | C46: ='Annual Model'!C125 -> -154 | D46: ='Annual Model'!D125 -> -145 | E46: ='Annual Model'!E125 -> -188 | F46: ='Annual Model'!F125 -> -156 | G46: -156 | H46: -156 | I46: -156 | J46: -156 | K46: -156 | L46: -156 | M46: -156
B48: Effect of Exchange Rate Changes on Cash & Cash Equivalents: | C48: ='Annual Model'!C129 -> 76 | D48: ='Annual Model'!D129 -> -34 | E48: ='Annual Model'!E129 -> -68 | F48: ='Annual Model'!F129 -> 3 | G48: 0 | H48: 0 | I48: 0 | J48: 0 | K48: 0 | L48: 0 | M48: 0

Sheet IS Scenario Analysis
B1: Home Depot (NYSE: HD)
B2: Scenario Analysis
C4: Historicals | G4: Projections
B5: Period End: | C5: =DATE(2021,1,31) -> 44227 | D5: =DATE(2022,1,30) -> 44591 | E5: =DATE(2022,1,29) -> 44590 | F5: =DATE(2024,1,28) -> 45319
B6: USD millions (expect per share data) | C6: FY2021A | D6: FY2022A | E6: FY2023A | F6: FY2024A | G6: FY2025E | H6: FY2026E | I6: FY2027E | J6: FY2028E | K6: FY2029E | L6: FY2030E | M6: FY2031E
B8: Scenario Selection | C8: 1
B13: Scenario
B14: Bull Case Scenario (2)
B15: Revenue Growth | G15: 0.02 | H15: 0.03 | I15: 0.04 | J15: 0.045 | K15: 0.045 | L15: 0.04 | M15: 0.04
B16: COGS % Rev | G16: 0.66 | H16: 0.6605 | I16: 0.661 | J16: 0.6615 | K16: 0.662 | L16: 0.6625 | M16: 0.663
B17: SG&A % Rev | G17: 0.171 | H17: 0.171 | I17: 0.171 | J17: 0.171 | K17: 0.171 | L17: 0.171 | M17: 0.171
B18: Depreciation % Rev | G18: 0.0155 | H18: 0.0155 | I18: 0.0155 | J18: 0.0155 | K18: 0.0155 | L18: 0.0155 | M18: 0.0155
B20: Base Case Scenario (1)
B21: Revenue Growth | G21: 0.01 | H21: 0.03 | I21: 0.034 | J21: 0.043 | K21: 0.0375 | L21: 0.0375 | M21: 0.035
B22: COGS % Rev | G22: 0.667 | H22: 0.6675 | I22: 0.668 | J22: 0.6685 | K22: 0.6685 | L22: 0.669 | M22: 0.6695
B23: SG&A % Rev | G23: 0.1736 | H23: 0.1736 | I23: 0.1736 | J23: 0.1736 | K23: 0.1736 | L23: 0.1736 | M23: 0.1736
B24: Depreciation % Rev | G24: 0.0162 | H24: 0.0162 | I24: 0.0162 | J24: 0.0162 | K24: 0.0162 | L24: 0.0162 | M24: 0.0162
B26: Bear Case Scenario (3)
B27: Revenue Growth | G27: 0.01 | H27: 0.02 | I27: 0.0275 | J27: 0.03 | K27: 0.035 | L27: 0.035 | M27: 0.037
B28: COGS % Rev | G28: 0.67 | H28: 0.6705 | I28: 0.671 | J28: 0.6715 | K28: 0.672 | L28: 0.6725 | M28: 0.673
B29: SG&A % Rev | G29: 0.175 | H29: 0.175 | I29: 0.175 | J29: 0.175 | K29: 0.175 | L29: 0.175 | M29: 0.175
B30: Depreciation % Rev | G30: 0.017 | H30: 0.017 | I30: 0.017 | J30: 0.017 | K30: 0.017 | L30: 0.017 | M30: 0.017
B34: Income Statement
B35: Revenue | C35: 132110 | D35: 151157 | E35: 157403 | F35: 152669 | G35: =F35*(1+CHOOSE($C$8,G21,G15,G27)) -> 154195.69 | H35: =G35*(1+CHOOSE($C$8,H21,H15,H27)) -> 158821.56 | I35: =H35*(1+CHOOSE($C$8,I21,I15,I27)) -> 164221.49 | J35: =I35*(1+CHOOSE($C$8,J21,J15,J27)) -> 171283.02 | K35: =J35*(1+CHOOSE($C$8,K21,K15,K27)) -> 177706.13 | L35: =K35*(1+CHOOSE($C$8,L21,L15,L27)) -> 184370.11 | M35: =L35*(1+CHOOSE($C$8,M21,M15,M27)) -> 190823.06
B36: Cost of Sales | C36: 87257 | D36: 100325 | E36: 104625 | F36: 101709 | G36: =G35*CHOOSE($C$8,G22,G16,G28) -> 102848.53 | H36: =H35*CHOOSE($C$8,H22,H16,H28) -> 106013.39 | I36: =I35*CHOOSE($C$8,I22,I16,I28) -> 109699.96 | J36: =J35*CHOOSE($C$8,J22,J16,J28) -> 114502.7 | K36: =K35*CHOOSE($C$8,K22,K16,K28) -> 118796.55 | L36: =L35*CHOOSE($C$8,L22,L16,L28) -> 123343.6 | M36: =M35*CHOOSE($C$8,M22,M16,M28) -> 127756.04
B37: Gross Profit | C37: =C35-C36 -> 44853 | D37: =D35-D36 -> 50832 | E37: =E35-E36 -> 52778 | F37: =F35-F36 -> 50960 | G37: =G35-G36 -> 51347.165 | H37: =H35-H36 -> 52808.169 | I37: =I35-I36 -> 54521.536 | J37: =J35-J36 -> 56780.32 | ... M37: =M35-M36 -> 63067.023
B38: Operating Expenses
B39: Selling, General, and Administrative: | C39: 24447 | D39: 25406 | E39: 26284 | F39: 26598 | G39: =G35*CHOOSE($C$8,G23,G17,G29) -> 26768.372 | H39: =H35*CHOOSE($C$8,H23,H17,H29) -> 27571.423 | I39: =I35*CHOOSE($C$8,I23,I17,I29) -> 28508.851 | J39: =J35*CHOOSE($C$8,J23,J17,J29) -> 29734.732 | K39: =K35*CHOOSE($C$8,K23,K17,K29) -> 30849.784 | L39: =L35*CHOOSE($C$8,L23,L17,L29) -> 32006.651 | M39: =M35*CHOOSE($C$8,M23,M17,M29) -> 33126.884
B40: EBITDA | C40: =C42+C41 -> 20406 | D40: =D42+D41 -> 25426 | E40: =E42+E41 -> 26494 | F40: =F42+F41 -> 24362 | G40: =G42+G41 -> 24578.793 | H40: =H42+H41 -> 25236.746 | I40: =I42+I41 -> 26012.685 | J40: =J42+J41 -> 27045.589 | ... M40: =M42+M41 -> 29940.139
B41: Depreciation and Amortization | C41: 2128 | D41: 2386 | E41: 2455 | F41: 2673 | G41: =G35*CHOOSE($C$8,G24,G18,G30) -> 2497.9702 | H41: =H35*CHOOSE($C$8,H24,H18,H30) -> 2572.9093 | I41: =I35*CHOOSE($C$8,I24,I18,I30) -> 2660.3882 | J41: =J35*CHOOSE($C$8,J24,J18,J30) -> 2774.7849 | K41: =K35*CHOOSE($C$8,K24,K18,K30) -> 2878.8393 | L41: =L35*CHOOSE($C$8,L24,L18,L30) -> 2986.7958 | M41: =M35*CHOOSE($C$8,M24,M18,M30) -> 3091.3337
B42: EBIT | C42: =C37-C39-C41 -> 18278 | D42: =D37-D39-D41 -> 23040 | E42: =E37-E39-E41 -> 24039 | F42: =F37-F39-F41 -> 21689 | G42: =G37-G39-G41 -> 22080.823 | H42: =H37-H39-H41 -> 22663.837 | I42: =I37-I39-I41 -> 23352.296 | J42: =J37-J39-J41 -> 24270.804 | ... M42: =M37-M39-M41 -> 26848.805
B43: Interest & Other (Income) Expense
B44: Interest and Investment Income: | C44: -47 | D44: -44 | E44: -55 | F44: -178 | G44: =-'Annual Model'!G274 -> -58.881795 | H44: =-'Annual Model'!H274 -> -100.59525 | I44: =-'Annual Model'!I274 -> -121.50485 | J44: =-'Annual Model'!J274 -> -147.77248 | K44: =-'Annual Model'!K274 -> -182.6769 | L44: =-'Annual Model'!L274 -> -224.2935 | M44: =-'Annual Model'!M274 -> -273.17456
B45: Interest Expense: | C45: 1347 | D45: 1347 | E45: 1617 | F45: 1943 | G45: ='Annual Model'!G272 -> 2132.73 | H45: ='Annual Model'!H272 -> 2059.58 | I45: ='Annual Model'!I272 -> 1949.38 | J45: ='Annual Model'!J272 -> 1843.93 | K45: ='Annual Model'!K272 -> 1748.93 | L45: ='Annual Model'!L272 -> 1653.93 | M45: ='Annual Model'!M272 -> 1558.93
B46: Net Interest & Other | C46: =SUM(C44:C45) -> 1300 | D46: =SUM(D44:D45) -> 1303 | E46: =SUM(E44:E45) -> 1562 | F46: =SUM(F44:F45) -> 1765 | G46: =SUM(G44:G45) -> 2073.8482 | H46: =SUM(H44:H45) -> 1958.9848 | I46: =SUM(I44:I45) -> 1827.8752 | J46: =SUM(J44:J45) -> 1696.1575 | ... M46: =SUM(M44:M45) -> 1285.7554
B47: EBT | C47: =C42-C46 -> 16978 | D47: =D42-D46 -> 21737 | E47: =E42-E46 -> 22477 | F47: =F42-F46 -> 19924 | G47: =G42-G46 -> 20006.975 | H47: =H42-H46 -> 20704.852 | I47: =I42-I46 -> 21524.421 | J47: =J42-J46 -> 22574.646 | ... M47: =M42-M46 -> 25563.05
B48: Provision for Income Taxes | C48: 4112 | D48: 5304 | E48: 5372 | F48: 4781 | G48: ='Annual Model'!G23 -> 4800.4644 | H48: ='Annual Model'!H23 -> 4948.86 | I48: ='Annual Model'!I23 -> 5157.4451 | J48: ='Annual Model'!J23 -> 5388.3447 | K48: ='Annual Model'!K23 -> 5608.3384 | L48: ='Annual Model'!L23 -> 5820.9225 | M48: ='Annual Model'!M23 -> 6025.0209
B49: Income Tax Expense (%): | C49: =C48/C47 -> 0.24219578 | D49: =D48/D47 -> 0.24400791 | E49: =E48/E47 -> 0.23899987 | F49: =F48/F47 -> 0.23996186 | G49: ='Annual Model'!G24 -> 0.24 | H49: ='Annual Model'!H24 -> 0.24 | I49: ='Annual Model'!I24 -> 0.24 | J49: ='Annual Model'!J24 -> 0.24 | K49: ='Annual Model'!K24 -> 0.24 | L49: ='Annual Model'!L24 -> 0.24 | M49: ='Annual Model'!M24 -> 0.24
B50: Net Earnings (Net Income) | C50: =C47-C48 -> 12866 | D50: =D47-D48 -> 16433 | E50: =E47-E48 -> 17105 | F50: =F47-F48 -> 15143 | G50: =G47-G48 -> 15206.51 | H50: =H47-H48 -> 15755.992 | I50: =I47-I48 -> 16366.976 | J50: =J47-J48 -> 17186.301 | ... M50: =M47-M48 -> 19538.029
B51: Earnings Per Share
B52: Basic EPS | C52: 11.98 | D52: 15.59 | E52: 16.74 | F52: 15.16 | G52: =G50/G55 -> 15.282925 | H52: =H50/H55 -> 15.883056 | I52: =I50/I55 -> 16.532299 | J52: =J50/J55 -> 17.395042 | K52: =K50/K55 -> 18.262036 | L52: =L50/L55 -> 19.049189 | M52: =M50/M55 -> 19.85572
B53: Diluted EPS | C53: 11.94 | D53: 15.53 | E53: 16.69 | F53: 15.11 | G53: =G50/G56 -> 15.252267 | H53: =H50/H56 -> 15.835168 | I53: =I50/I56 -> 16.498968 | J53: =J50/J56 -> 17.3599 | K53: =K50/K56 -> 18.225068 | L53: =L50/L56 -> 19.010628 | M53: =M50/M56 -> 19.815445
B54: Shares Used in Computing EPS
B55: Basic Weighted Average Common Shares | C55: 1074 | D55: 1054 | E55: 1022 | F55: 999 | G55: ='Annual Model'!G30 -> 995 | H55: ='Annual Model'!H30 -> 992 | I55: ='Annual Model'!I30 -> 990 | J55: ='Annual Model'!J30 -> 988 | K55: ='Annual Model'!K30 -> 986 | L55: ='Annual Model'!L30 -> 986 | M55: ='Annual Model'!M30 -> 984
B56: Diluted Weighted Average Common Shares | C56: 1078 | D56: 1058 | E56: 1025 | F56: 1002 | G56: ='Annual Model'!G31 -> 997 | H56: ='Annual Model'!H31 -> 995 | I56: ='Annual Model'!I31 -> 992 | J56: ='Annual Model'!J31 -> 990 | K56: ='Annual Model'!K31 -> 988 | L56: ='Annual Model'!L31 -> 988 | M56: ='Annual Model'!M31 -> 986

Sheet Annual Model
B1: Home Depot (NYSE: HD)
B2: Annual Financial Model
B3: Financial Statements & Supporting Schedules
B5: Period End: | C5: =DATE(2021,1,31) -> 44227 | D5: =DATE(2022,1,30) -> 44591 | E5: =DATE(2022,1,29) -> 44590 | F5: =DATE(2024,1,28) -> 45319
B6: USD millions (expect per share data) | C6: FY2021A | D6: FY2022A | E6: FY2023A | F6: FY2024A | G6: FY2025E | H6: FY2026E | I6: FY2027E | J6: FY2028E | K6: FY2029E | L6: FY2030E | M6: FY2031E
C8: Historical | G8: Projections
B9: Income Statement
B10: Revenue | C10: 132110 | D10: 151157 | E10: 157403 | F10: 152669 | G10: =F10*(1+Assumptions!G10) -> 154195.69 | H10: =G10*(1+Assumptions!H10) -> 158821.56 | I10: =H10*(1+Assumptions!I10) -> 165174.42 | J10: =I10*(1+Assumptions!J10) -> 172276.92 | K10: =J10*(1+Assumptions!K10) -> 179168 | L10: =K10*(1+Assumptions!L10) -> 185886.8 | M10: =L10*(1+Assumptions!M10) -> 192392.84
B11: Cost of Sales | C11: 87257 | D11: 100325 | E11: 104625 | F11: 101709 | G11: =G10*Assumptions!G11 -> 102848.53 | H11: =H10*Assumptions!H11 -> 106092.8 | I11: =I10*Assumptions!I11 -> 110501.69 | J11: =J10*Assumptions!J11 -> 115425.54 | K11: =K10*Assumptions!K11 -> 120221.73 | L11: =L10*Assumptions!L11 -> 124915.93 | M11: =M10*Assumptions!M11 -> 129480.38
B12: Gross Profit | C12: =C10-C11 -> 44853 | D12: =D10-D11 -> 50832 | E12: =E10-E11 -> 52778 | F12: =F10-F11 -> 50960 | G12: =G10-G11 -> 51347.165 | H12: =H10-H11 -> 52728.758 | I12: =I10-I11 -> 54672.734 | J12: =J10-J11 -> 56851.385 | ... M12: =M10-M11 -> 62912.458
B13: Operating Expenses
B14: Selling, General, and Administrative: | C14: 24447 | D14: 25406 | E14: 26284 | F14: 26598 | G14: =G10*Assumptions!G12 -> 26765.776 | H14: =H10*Assumptions!H12 -> 27568.749 | I14: =I10*Assumptions!I12 -> 28671.499 | J14: =J10*Assumptions!J12 -> 29904.374 | K14: =K10*Assumptions!K12 -> 31100.549 | L14: =L10*Assumptions!L12 -> 32266.819 | M14: =M10*Assumptions!M12 -> 33396.158
B15: EBITDA | C15: =C17+C16 -> 20406 | D15: =D17+D16 -> 25426 | E15: =E17+E16 -> 26494 | F15: =F17+F16 -> 24362 | G15: =G17+G16 -> 24581.389 | H15: =H17+H16 -> 25160.009 | I15: =I17+I16 -> 26001.235 | J15: =J17+J16 -> 26947.011 | ... M15: =M17+M16 -> 29516.3
B16: Depreciation and Amortization | C16: 2128 | D16: 2386 | E16: 2455 | F16: 2673 | G16: =Assumptions!G13*'Annual Model'!G10 -> 2505.6057 | H16: =Assumptions!H13*'Annual Model'!H10 -> 2580.7739 | I16: =Assumptions!I13*'Annual Model'!I10 -> 2684.0049 | J16: =Assumptions!J13*'Annual Model'!J10 -> 2799.4171 | K16: =Assumptions!K13*'Annual Model'!K10 -> 2911.3938 | L16: =Assumptions!L13*'Annual Model'!L10 -> 3020.571 | M16: =Assumptions!M13*'Annual Model'!M10 -> 3126.291
B17: EBIT | C17: =C12-C14-C16 -> 18278 | D17: =D12-D14-D16 -> 23040 | E17: =E12-E14-E16 -> 24039 | F17: =F12-F14-F16 -> 21689 | G17: =G12-G14-G16 -> 22075.783 | H17: =H12-H14-H16 -> 22579.235 | I17: =I12-I14-I16 -> 23317.23 | J17: =J12-J14-J16 -> 24147.594 | ... M17: =M12-M14-M16 -> 26390.009
B18: Interest & Other (Income) Expense
B19: Interest and Investment Income: | C19: -47 | D19: -44 | E19: -55 | F19: -178 | G19: =-G274 -> -58.881795 | H19: =-H274 -> -100.59525 | I19: =-I274 -> -121.50485 | J19: =-J274 -> -147.77248 | K19: =-K274 -> -182.6769 | L19: =-L274 -> -224.2935 | M19: =-M274 -> -273.17456
B20: Interest Expense: | C20: 1347 | D20: 1347 | E20: 1617 | F20: 1943 | G20: =G272 -> 2132.73 | H20: =H272 -> 2059.58 | I20: =I272 -> 1949.38 | J20: =J272 -> 1843.93 | K20: =K272 -> 1748.93 | L20: =L272 -> 1653.93 | M20: =M272 -> 1558.93
B21: Net Interest & Other | C21: =SUM(C19:C20) -> 1300 | D21: =SUM(D19:D20) -> 1303 | E21: =SUM(E19:E20) -> 1562 | F21: =SUM(F19:F20) -> 1765 | G21: =SUM(G19:G20) -> 2073.8482 | H21: =SUM(H19:H20) -> 1958.9848 | I21: =SUM(I19:I20) -> 1827.8752 | J21: =SUM(J19:J20) -> 1696.1575 | ... M21: =SUM(M19:M20) -> 1285.7554
B22: EBT | C22: =C17-C21 -> 16978 | D22: =D17-D21 -> 21737 | E22: =E17-E21 -> 22477 | F22: =F17-F21 -> 19924 | G22: =G17-G21 -> 20001.935 | H22: =H17-H21 -> 20620.25 | I22: =I17-I21 -> 21489.355 | J22: =J17-J21 -> 22451.436 | ... M22: =M17-M21 -> 25104.254
B23: Provision for Income Taxes | C23: 4112 | D23: 5304 | E23: 5372 | F23: 4781 | G23: =G24*G22 -> 4800.4644 | H23: =H24*H22 -> 4948.86 | I23: =I24*I22 -> 5157.4451 | J23: =J24*J22 -> 5388.3447 | K23: =K24*K22 -> 5608.3384 | L23: =L24*L22 -> 5820.9225 | M23: =M24*M22 -> 6025.0209
B24: Income Tax Expense (%): | C24: =C23/C22 -> 0.24219578 | D24: =D23/D22 -> 0.24400791 | E24: =E23/E22 -> 0.23899987 | F24: =F23/F22 -> 0.23996186 | G24: =Assumptions!G14 -> 0.24 | H24: =Assumptions!H14 -> 0.24 | I24: =Assumptions!I14 -> 0.24 | J24: =Assumptions!J14 -> 0.24 | K24: =Assumptions!K14 -> 0.24 | L24: =Assumptions!L14 -> 0.24 | M24: =Assumptions!M14 -> 0.24
B25: Net Earnings (Net Income) | C25: =C22-C23 -> 12866 | D25: =D22-D23 -> 16433 | E25: =E22-E23 -> 17105 | F25: =F22-F23 -> 15143 | G25: =G22-G23 -> 15201.47 | H25: =H22-H23 -> 15671.39 | I25: =I22-I23 -> 16331.91 | J25: =J22-J23 -> 17063.092 | ... M25: =M22-M23 -> 19079.233
B26: Earnings Per Share
B27: Basic EPS | C27: 11.98 | D27: 15.59 | E27: 16.74 | F27: 15.16 | G27: =G25/G30 -> 15.27786 | H27: =H25/H30 -> 15.797772 | I27: =I25/I30 -> 16.496878 | J27: =J25/J30 -> 17.270336 | K27: =K25/K30 -> 18.011905 | L27: =L25/L30 -> 18.694646 | M27: =M25/M30 -> 19.389464
B28: Diluted EPS | C28: 11.94 | D28: 15.53 | E28: 16.69 | F28: 15.11 | G28: =G25/G31 -> 15.247212 | H28: =H25/H31 -> 15.750141 | I28: =I25/I31 -> 16.463619 | J28: =J25/J31 -> 17.235446 | K28: =K25/K31 -> 17.975443 | L28: =L25/L31 -> 18.656803 | M28: =M25/M31 -> 19.350135
B29: Shares Used in Computing EPS
B30: Basic Weighted Average Common Shares | C30: 1074 | D30: 1054 | E30: 1022 | F30: 999 | G30: =Assumptions!G15 -> 995 | H30: =Assumptions!H15 -> 992 | I30: =Assumptions!I15 -> 990 | J30: =Assumptions!J15 -> 988 | K30: =Assumptions!K15 -> 986 | L30: =Assumptions!L15 -> 986 | M30: =Assumptions!M15 -> 984
B31: Diluted Weighted Average Common Shares | C31: 1078 | D31: 1058 | E31: 1025 | F31: 1002 | G31: =Assumptions!G17 -> 997 | H31: =Assumptions!H17 -> 995 | I31: =Assumptions!I17 -> 992 | J31: =Assumptions!J17 -> 990 | K31: =Assumptions!K17 -> 988 | L31: =Assumptions!L17 -> 988 | M31: =Assumptions!M17 -> 986
B36: Balance Sheet
B37: Assets
B38: Cash & Cash Equivalents: | C38: 2133 | D38: 7895 | E38: 2343 | F38: 2757 | G38: =F38+G128 -> 7919.359 | H38: =G38+H128 -> 7249.6904 | I38: =H38+I128 -> 6301.2789 | J38: =I38+J128 -> 6953.2177 | K38: =J38+K128 -> 8282.163 | L38: =K38+L128 -> 10276.537 | M38: =L38+M128 -> 13058.375
B39: Receivables, Net: | C39: 2106 | D39: 2992 | E39: 3426 | F39: 3317 | G39: =F39-G97 -> 3404.9788 | H39: =G39-H97 -> 3507.1282 | I39: =H39-I97 -> 3647.4133 | J39: =I39-J97 -> 3804.2521 | K39: =J39-K97 -> 3956.4221 | L39: =K39-L97 -> 4104.788 | M39: =L39-M97 -> 4248.4556
B40: Merchandise Inventories: | C40: 14531 | D40: 16627 | E40: 22068 | F40: 24886 | G40: =F40-G98 -> 23740.031 | H40: =G40-H98 -> 24488.544 | I40: =H40-I98 -> 25506.212 | J40: =I40-J98 -> 26642.744 | K40: =J40-K98 -> 27749.81 | L40: =K40-L98 -> 28833.334 | M40: =L40-M98 -> 29886.91
B41: Other Current Assets: | C41: 1040 | D41: 963 | E41: 1218 | F41: 1511 | G41: =F41-G94-G123 -> 1382.5 | H41: =G41-H94-H123 -> 1254 | I41: =H41-I94-I123 -> 1125.5 | J41: =I41-J94-J123 -> 997 | K41: =J41-K94-K123 -> 868.5 | L41: =K41-L94-L123 -> 740 | M41: =L41-M94-M123 -> 611.5
B42: Total Current Assets | C42: =SUM(C38:C41) -> 19810 | D42: =SUM(D38:D41) -> 28477 | E42: =SUM(E38:E41) -> 29055 | F42: =SUM(F38:F41) -> 32471 | G42: =SUM(G38:G41) -> 36446.869 | H42: =SUM(H38:H41) -> 36499.363 | I42: =SUM(I38:I41) -> 36580.404 | J42: =SUM(J38:J41) -> 38397.214 | ... M42: =SUM(M38:M41) -> 47805.24
B44: Net Property & Equipment | C44: 22770 | D44: 24705 | E44: 25199 | F44: 25631 | G44: =F44-G108-G88-G109-G110 -> 25303.518 | H44: =G44-H108-H88-H109-H110 -> 24909.732 | I44: =H44-I108-I88-I109-I110 -> 24477.829 | J44: =I44-J108-J88-J109-J110 -> 24015.699 | K44: =J44-K108-K88-K109-K110 -> 23512.222 | L44: =K44-L108-L88-L109-L110 -> 22957.235 | M44: =L44-M108-M88-M109-M110 -> 22339.975
B45: Operating Lease ROU Assets | C45: 5595 | D45: 5962 | E45: 5968 | F45: 6941 | G45: =Assumptions!G22 -> 6941 | H45: =Assumptions!H22 -> 6941 | I45: =Assumptions!I22 -> 6941 | J45: =Assumptions!J22 -> 6941 | K45: =Assumptions!K22 -> 6941 | L45: =Assumptions!L22 -> 6941 | M45: =Assumptions!M22 -> 6941
B46: Goodwill | C46: 2254 | D46: 7126 | E46: 7449 | F46: 7444 | G46: =Assumptions!G23 -> 7444 | H46: =Assumptions!H23 -> 7444 | I46: =Assumptions!I23 -> 7444 | J46: =Assumptions!J23 -> 7444 | K46: =Assumptions!K23 -> 7444 | L46: =Assumptions!L23 -> 7444 | M46: =Assumptions!M23 -> 7444
B47: Intangible Assets: | C47: 0 | D47: 0 | E47: 0 | F47: 0 | G47: =F47-G89 -> 0 | H47: =G47-H89 -> 0 | I47: =H47-I89 -> 0 | J47: =I47-J89 -> 0 | K47: =J47-K89 -> 0 | L47: =K47-L89 -> 0 | M47: =L47-M89 -> 0
B48: Other Assets | C48: 807 | D48: 4311 | E48: 4205 | F48: 3958 | G48: =F48-G95-G111 -> 3593.3499 | H48: =G48-H95-H111 -> 3186.296 | I48: =H48-I95-I111 -> 2730.3251 | J48: =I48-J95-J111 -> 2220.722 | K48: =J48-K95-K111 -> 1655.3012 | L48: =K48-L95-L111 -> 1031.8747 | M48: =L48-M95-M111 -> 348.49982
B49: Total Non-Current Assets | C49: =SUM(C44:C48) -> 31426 | D49: =SUM(D44:D48) -> 42104 | E49: =SUM(E44:E48) -> 42821 | F49: =SUM(F44:F48) -> 43974 | G49: =SUM(G44:G48) -> 43281.868 | H49: =SUM(H44:H48) -> 42481.028 | I49: =SUM(I44:I48) -> 41593.154 | J49: =SUM(J44:J48) -> 40621.421 | ... M49: =SUM(M44:M48) -> 37073.475
B50: Total Assets | C50: =C42+C49 -> 51236 | D50: =D42+D49 -> 70581 | E50: =E42+E49 -> 71876 | F50: =F42+F49 -> 76445 | G50: =G42+G49 -> 79728.737 | H50: =H42+H49 -> 78980.391 | I50: =I42+I49 -> 78173.558 | J50: =J42+J49 -> 79018.635 | ... M50: =M42+M49 -> 84878.715
B52: Liabilities & Stockholders' Equity
B53: Short-Term Debt: | C53: 974 | D53: 0 | E53: 1035 | F53: 0 | G53: =F53+G115 -> 0 | H53: =G53+H115 -> 0 | I53: =H53+I115 -> 0 | J53: =I53+J115 -> 0 | K53: =J53+K115 -> 0 | L53: =K53+L115 -> 0 | M53: =L53+M115 -> 0
B54: Accounts Payable: | C54: 7787 | D54: 11606 | E54: 13462 | F54: 11443 | G54: =F54+G99 -> 12592.015 | H54: =G54+H99 -> 12989.828 | I54: =H54+I99 -> 13529.645 | J54: =I54+J99 -> 14132.513 | K54: =J54+K99 -> 14719.751 | L54: =K54+L99 -> 15294.501 | M54: =L54+M99 -> 15853.365
B55: Accrued Salaries and Related Expenses: | C55: 1494 | D55: 2463 | E55: 2426 | F55: 1991 | G55: =F55+G100 -> 2222.4309 | H55: =G55+H100 -> 2289.3392 | I55: =H55+I100 -> 2380.9127 | J55: =I55+J100 -> 2483.292 | K55: =J55+K100 -> 2582.6236 | L55: =K55+L100 -> 2679.472 | M55: =L55+M100 -> 2773.2536
B56: Stock Based Compensation Expense: | C56: 0 | D56: 0 | E56: 0 | F56: 0 | G56: =F56+G90 -> 385.48923 | H56: =G56+H90 -> 782.54313 | I56: =H56+I90 -> 1195.4792 | J56: =I56+J90 -> 1626.1715 | K56: =J56+K90 -> 2074.0915 | L56: =K56+L90 -> 2538.8085 | M56: =L56+M90 -> 3019.7906
B57: Sales Taxes Payable: | C57: 605 | D57: 774 | E57: 848 | F57: 528 | G57: =F57+G102 -> 690.80098 | H57: =G57+H102 -> 712.09351 | I57: =H57+I102 -> 742.1069 | J57: =I57+J102 -> 775.33114 | K57: =J57+K102 -> 806.98611 | L57: =K57+L102 -> 837.57493 | M57: =L57+M102 -> 866.94273
B58: Deferred Revenue: | C58: 2116 | D58: 2823 | E58: 3596 | F58: 3064 | G58: =F58+G92 -> 3295.2935 | H58: =G58+H92 -> 3533.5259 | I58: =H58+I92 -> 3781.2875 | J58: =I58+J92 -> 4039.7029 | K58: =J58+K92 -> 4308.4549 | L58: =K58+L92 -> 4587.2851 | M58: =L58+M92 -> 4875.8744
B59: Income Taxes Payable | C59: 55 | D59: 193 | E59: 158 | F59: 50 | G59: =F59+G101 -> 104.4234 | H59: =G59+H101 -> 107.65465 | I59: =H59+I101 -> 112.19209 | J59: =I59+J101 -> 117.21495 | K59: =J59+K101 -> 122.00057 | L59: =K59+L101 -> 126.625 | M59: =L59+M101 -> 131.06484
B60: Current Installments of Long-Term Debt: | C60: 1839 | D60: 1416 | E60: 2447 | F60: 1231 | G60: =F60 -> 1231 | H60: =G60 -> 1231 | I60: =H60 -> 1231 | J60: =I60 -> 1231 | K60: =J60 -> 1231 | L60: =K60 -> 1231 | M60: =L60 -> 1231
B61: Current Operating Lease Liabilities: | C61: 828 | D61: 828 | E61: 830 | F61: 945 | G61: =F61 -> 945 | H61: =G61 -> 945 | I61: =H61 -> 945 | J61: =I61 -> 945 | K61: =J61 -> 945 | L61: =K61 -> 945 | M61: =L61 -> 945
B62: Other Accrued Expenses: | C62: 2677 | D62: 3063 | E62: 3891 | F62: 3858 | G62: =F62 -> 3858 | H62: =G62 -> 3858 | I62: =H62 -> 3858 | J62: =I62 -> 3858 | K62: =J62 -> 3858 | L62: =K62 -> 3858 | M62: =L62 -> 3858
B63: Total Current Liabilities | C63: =SUM(C53:C62) -> 18375 | D63: =SUM(D53:D62) -> 23166 | E63: =SUM(E53:E62) -> 28693 | F63: =SUM(F53:F62) -> 23110 | G63: =SUM(G53:G62) -> 25324.453 | H63: =SUM(H53:H62) -> 26448.985 | I63: =SUM(I53:I62) -> 27775.624 | J63: =SUM(J53:J62) -> 29208.226 | ... M63: =SUM(M53:M62) -> 33554.291
B65: Long-Term Debt, Excluding Current Installments: | C65: 28670 | D65: 35822 | E65: 36604 | F65: 41962 | G65: =F65+G116+G117 -> 39762 | H65: =G65+H116+H117 -> 34262 | I65: =H65+I116+I117 -> 28162 | J65: =I65+J116+J117 -> 23162 | K65: =J65+K116+K117 -> 18162 | L65: =K65+L116+L117 -> 13162 | M65: =L65+M116+M117 -> 8162
B66: Long-Term Operating Lease Liabilities: | C66: 5066 | D66: 5356 | E66: 5353 | F66: 6226 | G66: =F66 -> 6226 | H66: =G66 -> 6226 | I66: =H66 -> 6226 | J66: =I66 -> 6226 | K66: =J66 -> 6226 | L66: =K66 -> 6226 | M66: =L66 -> 6226
B67: Deferred Income Taxes: | C67: 706 | D67: 1131 | E67: 909 | F67: 1019 | G67: =F67+G93 -> 1697.8134 | H67: =G67+H93 -> 2386.3456 | I67: =H67+I93 -> 2883.9641 | J67: =I67+J93 -> 3225.9472 | K67: =J67+K93 -> 3440.3108 | L67: =K67+L93 -> 3548.681 | M67: =L67+M93 -> 3665.7701
B68: Other Long-Term Liabilities: | C68: 1535 | D68: 1807 | E68: 2013 | F68: 2566 | G68: =F68 -> 2566 | H68: =G68 -> 2566 | I68: =H68 -> 2566 | J68: =I68 -> 2566 | K68: =J68 -> 2566 | L68: =K68 -> 2566 | M68: =L68 -> 2566
B69: Total Non-Current Liabilities | C69: =SUM(C65:C68) -> 35977 | D69: =SUM(D65:D68) -> 44116 | E69: =SUM(E65:E68) -> 44879 | F69: =SUM(F65:F68) -> 51773 | G69: =SUM(G65:G68) -> 50251.813 | H69: =SUM(H65:H68) -> 45440.346 | I69: =SUM(I65:I68) -> 39837.964 | J69: =SUM(J65:J68) -> 35179.947 | ... M69: =SUM(M65:M68) -> 20619.77
B70: Total Liabilities | C70: =C63+C69 -> 54352 | D70: =D63+D69 -> 67282 | E70: =E63+E69 -> 73572 | F70: =F63+F69 -> 74883 | G70: =G63+G69 -> 75576.266 | H70: =H63+H69 -> 71889.33 | I70: =I63+I69 -> 67613.588 | J70: =J63+J69 -> 64388.173 | ... M70: =M63+M69 -> 54174.061
B72: Stockholders' Equity
B73: Common Stock: | C73: 89 | D73: 89 | E73: 90 | F73: 90 | G73: =F73 -> 90 | H73: =G73 -> 90 | I73: =H73 -> 90 | J73: =I73 -> 90 | K73: =J73 -> 90 | L73: =K73 -> 90 | M73: =L73 -> 90
B74: Paid-in Capital: | C74: 11001 | D74: 11540 | E74: 12132 | F74: 12592 | G74: =F74 -> 12592 | H74: =G74 -> 12592 | I74: =H74 -> 12592 | J74: =I74 -> 12592 | K74: =J74 -> 12592 | L74: =K74 -> 12592 | M74: =L74 -> 12592
B75: Retained Earnings: | C75: 51729 | D75: 58134 | E75: 67580 | F75: 76896 | G75: =F75+G87+G124+G122 -> 79642.47 | H75: =G75+H87+H124+H122 -> 82737.061 | I75: =H75+I87+I124+I122 -> 86361.97 | J75: =I75+J87+J124+J122 -> 90588.462 | K75: =J75+K87+K124+K122 -> 95481.2 | L75: =K75+L87+L124+L122 -> 100997.82 | M75: =L75+M87+M124+M122 -> 107130.65
B76: Accumulated Other Comprehensive (Income) Loss: | C76: -739 | D76: -671 | E76: -704 | F76: -718 | G76: =F76+G129+G91+G125 -> -874 | H76: =G76+H129+H91+H125 -> -1030 | I76: =H76+I129+I91+I125 -> -1186 | J76: =I76+J129+J91+J125 -> -1342 | K76: =J76+K129+K91+K125 -> -1498 | L76: =K76+L129+L91+L125 -> -1654 | M76: =L76+M129+M91+M125 -> -1810
B77: Treasury Stock | C77: -65196 | D77: -65793 | E77: -80794 | F77: -87298 | G77: =F77 -> -87298 | H77: =G77 -> -87298 | I77: =H77 -> -87298 | J77: =I77 -> -87298 | K77: =J77 -> -87298 | L77: =K77 -> -87298 | M77: =L77 -> -87298
B78: Total Stockholders' Equity (Deficit) | C78: =SUM(C73:C77) -> -3116 | D78: =SUM(D73:D77) -> 3299 | E78: =SUM(E73:E77) -> -1696 | F78: =SUM(F73:F77) -> 1562 | G78: =SUM(G73:G77) -> 4152.4704 | H78: =SUM(H73:H77) -> 7091.0606 | I78: =SUM(I73:I77) -> 10559.97 | J78: =SUM(J73:J77) -> 14630.462 | ... M78: =SUM(M73:M77) -> 30704.654
B79: Total Liabilties & Stockholders' Equity | C79: =C70+C78 -> 51236 | D79: =D70+D78 -> 70581 | E79: =E70+E78 -> 71876 | F79: =F70+F78 -> 76445 | G79: =G70+G78 -> 79728.737 | H79: =H70+H78 -> 78980.391 | I79: =I70+I78 -> 78173.558 | J79: =J70+J78 -> 79018.635 | ... M79: =M70+M78 -> 84878.715
B81: Balance Check: | C81: =IF(C50=C79, "Y", "N") -> Y | D81: =IF(D50=D79, "Y", "N") -> Y | E81: =IF(E50=E79, "Y", "N") -> Y | F81: =IF(F50=F79, "Y", "N") -> Y | G81: =IF(G50=G79, "Y", "N") -> Y | H81: =IF(H50=H79, "Y", "N") -> Y | I81: =IF(I50=I79, "Y", "N") -> Y | J81: =IF(J50=J79, "Y", "N") -> Y | ... M81: =IF(M50=M79, "Y", "N") -> Y
B85: Cash Flow Statement
B86: Operating Activities
B87: Net Earnings (Net Income): | C87: 12866 | D87: 16433 | E87: 17105 | F87: 15143 | G87: =G25 -> 15201.47 | H87: =H25 -> 15671.39 | I87: =I25 -> 16331.91 | J87: =J25 -> 17063.092 | K87: =K25 -> 17759.738 | L87: =L25 -> 18432.921 | M87: =M25 -> 19079.233
B88: Depreciation & Amortization: | C88: 2519 | D88: 2862 | E88: 2975 | F88: 3247 | G88: =G157 -> 3411.3957 | H88: =H157 -> 3570.2173 | I88: =I157 -> 3735.3917 | J88: =J157 -> 3907.6686 | K88: =K157 -> 4086.8366 | L88: =L157 -> 4272.7234 | M88: =M157 -> 4465.1162
B89: Intangible Asset Amortization: | G89: =Assumptions!G27 -> 0 | H89: =Assumptions!H27 -> 0 | I89: =Assumptions!I27 -> 0 | J89: =Assumptions!J27 -> 0 | K89: =Assumptions!K27 -> 0 | L89: =Assumptions!L27 -> 0 | M89: =Assumptions!M27 -> 0
B90: Stock-Based Compensation Expense: | C90: 310 | D90: 399 | E90: 366 | F90: 380 | G90: =Assumptions!G28 -> 385.48923 | H90: =Assumptions!H28 -> 397.0539 | I90: =Assumptions!I28 -> 412.93606 | J90: =Assumptions!J28 -> 430.69231 | K90: =Assumptions!K28 -> 447.92 | L90: =Assumptions!L28 -> 464.717 | M90: =Assumptions!M28 -> 480.9821
B91: Impairment Loss: | C91: 0 | G91: =Assumptions!G30 -> 0 | H91: =Assumptions!H30 -> 0 | I91: =Assumptions!I30 -> 0 | J91: =Assumptions!J30 -> 0 | K91: =Assumptions!K30 -> 0 | L91: =Assumptions!L30 -> 0 | M91: =Assumptions!M30 -> 0
B92: Changes in Deferred Revenue: | C92: 702 | D92: 775 | E92: -526 | F92: -318 | G92: =Assumptions!G32 -> 231.29354 | H92: =Assumptions!H32 -> 238.23234 | I92: =Assumptions!I32 -> 247.76163 | J92: =Assumptions!J32 -> 258.41538 | K92: =Assumptions!K32 -> 268.752 | L92: =Assumptions!L32 -> 278.8302 | M92: =Assumptions!M32 -> 288.58926
B93: Changes in Deferred Income Taxes: | C93: -569 | D93: -276 | E93: 138 | F93: -245 | G93: =G184 -> 678.81341 | H93: =H184 -> 688.53216 | I93: =I184 -> 497.61854 | J93: =J184 -> 341.98312 | K93: =K184 -> 214.36358 | L93: =L184 -> 108.37019 | M93: =M184 -> 117.08914
B94: Changes in Other Current Assets: | C94: 43 | D94: -330 | E94: -311 | F94: -184 | G94: =Assumptions!G31 -> -184 | H94: =Assumptions!H31 -> -184 | I94: =Assumptions!I31 -> -184 | J94: =Assumptions!J31 -> -184 | K94: =Assumptions!K31 -> -184 | L94: =Assumptions!L31 -> -184 | M94: =Assumptions!M31 -> -184
B95: Other Operating Activities: | C95: 121 | D95: 196 | E95: 271 | F95: 314 | G95: =Assumptions!G34 -> 354.65009 | H95: =Assumptions!H34 -> 397.0539 | I95: =Assumptions!I34 -> 445.97094 | J95: =Assumptions!J34 -> 499.60308 | K95: =Assumptions!K34 -> 555.4208 | L95: =Assumptions!L34 -> 613.42644 | M95: =Assumptions!M34 -> 673.37493
B97: Changes in Receivables, Net: | C97: -465 | D97: -435 | E97: 111 | F97: 134 | G97: =-(G190-F190) -> -87.978798 | H97: =-(H190-G190) -> -102.14936 | I97: =-(I190-H190) -> -140.28513 | J97: =-(J190-I190) -> -156.83877 | K97: =-(K190-J190) -> -152.17008 | L97: =-(L190-K190) -> -148.36583 | M97: =-(M190-L190) -> -143.66758
B98: Changes in Merchandise Inventories: | C98: -1657 | D98: -5403 | E98: -2830 | F98: 4137 | G98: =-(G192-F192) -> 1145.9689 | H98: =-(H192-G192) -> -748.51301 | I98: =-(I192-H192) -> -1017.6676 | J98: =-(J192-I192) -> -1136.5324 | K98: =-(K192-J192) -> -1107.0657 | L98: =-(L192-K192) -> -1083.5246 | M98: =-(M192-L192) -> -1053.5752
B99: Changes in Accounts Payable | C99: 5118 | D99: 2401 | E99: -2577 | F99: -1411 | G99: =G197-F197 -> 1149.0151 | H99: =H197-G197 -> 397.81328 | I99: =I197-H197 -> 539.81682 | J99: =J197-I197 -> 602.86805 | K99: =K197-J197 -> 587.23756 | L99: =L197-K197 -> 574.75033 | M99: =M197-L197 -> 558.8638
B100: Changes in Accrued Salaries & Related Expenses: | C100: 0 | D100: 0 | E100: 0 | F100: 0 | G100: =G199-F199 -> 231.43087 | H100: =H199-G199 -> 66.908282 | I100: =I199-H199 -> 91.573566 | J100: =J199-I199 -> 102.37925 | K100: =K199-J199 -> 99.331679 | L100: =L199-K199 -> 96.848387 | M100: =M199-L199 -> 93.781521
B101: Changes in Income Taxes Payable: | C101: -149 | D101: -51 | E101: -107 | F101: -25 | G101: =G203-F203 -> 54.423404 | H101: =H203-G203 -> 3.2312505 | I101: =I203-H203 -> 4.5374402 | J101: =J203-I203 -> 5.0228567 | K101: =K203-J203 -> 4.7856151 | L101: =L203-K203 -> 4.6244326 | M101: =M203-L203 -> 4.4398393
B102: Changes in Sales Taxes Payable: | C102: 0 | D102: 0 | E102: 0 | F102: 0 | G102: =G201-F201 -> 162.80098 | H102: =H201-G201 -> 21.292528 | I102: =I201-H201 -> 30.013395 | J102: =J201-I201 -> 33.224236 | K102: =K201-J201 -> 31.654976 | L102: =L201-K201 -> 30.588816 | M102: =M201-L201 -> 29.367804
B103: Net Changes in Operating Working Capital | C103: =SUM(C97:C102) -> 2847 | D103: =SUM(D97:D102) -> -3488 | E103: =SUM(E97:E102) -> -5403 | F103: =SUM(F97:F102) -> 2835 | G103: =SUM(G97:G102) -> 2655.6604 | H103: =SUM(H97:H102) -> -361.41704 | I103: =SUM(I97:I102) -> -492.01155 | J103: =SUM(J97:J102) -> -549.87678 | ... M103: =SUM(M97:M102) -> -510.7898
B105: Cash Flow From Operating Activities | C105: =SUM(C87:C102) -> 18839 | D105: =SUM(D87:D102) -> 16571 | E105: =SUM(E87:E102) -> 14615 | F105: =SUM(F87:F102) -> 21172 | G105: =SUM(G87:G102) -> 22734.773 | H105: =SUM(H87:H102) -> 20417.063 | I105: =SUM(I87:I102) -> 20995.577 | J105: =SUM(J87:J102) -> 21767.577 | ... M105: =SUM(M87:M102) -> 24409.595
B107: Investing Activities
B108: Capital Expenditures: | C108: -2463 | D108: -2566 | E108: -3119 | F108: -3226 | G108: =-Assumptions!G26*'Annual Model'!G10 -> -3083.9138 | H108: =-Assumptions!H26*'Annual Model'!H10 -> -3176.4312 | I108: =-Assumptions!I26*'Annual Model'!I10 -> -3303.4885 | J108: =-Assumptions!J26*'Annual Model'!J10 -> -3445.5385 | K108: =-Assumptions!K26*'Annual Model'!K10 -> -3583.36 | L108: =-Assumptions!L26*'Annual Model'!L10 -> -3717.736 | M108: =-Assumptions!M26*'Annual Model'!M10 -> -3847.8568
B109: Payments for Businesses Acquired: | C109: -7780 | D109: -421 | E109: 0 | F109: -1514 | G109: =Assumptions!G37 -> 0 | H109: =Assumptions!H37 -> 0 | I109: =Assumptions!I37 -> 0 | J109: =Assumptions!J37 -> 0 | K109: =Assumptions!K37 -> 0 | L109: =Assumptions!L37 -> 0 | M109: =Assumptions!M37 -> 0
B110: Proceeds from Sales of Property and Equipment: | G110: =-Assumptions!G38 -> 0 | H110: =-Assumptions!H38 -> 0 | I110: =-Assumptions!I38 -> 0 | J110: =-Assumptions!J38 -> 0 | K110: =-Assumptions!K38 -> 0 | L110: =-Assumptions!L38 -> 0 | M110: =-Assumptions!M38 -> 0
B111: Other Investing Activities: | C111: 73 | D111: 18 | E111: -21 | F111: 11 | G111: =Assumptions!G39 -> 10 | H111: =Assumptions!H39 -> 10 | I111: =Assumptions!I39 -> 10 | J111: =Assumptions!J39 -> 10 | K111: =Assumptions!K39 -> 10 | L111: =Assumptions!L39 -> 10 | M111: =Assumptions!M39 -> 10
B112: Cash Flow from Investing Activities | C112: =SUM(C108:C111) -> -10170 | D112: =SUM(D108:D111) -> -2969 | E112: =SUM(E108:E111) -> -3140 | F112: =SUM(F108:F111) -> -4729 | G112: =SUM(G108:G111) -> -3073.9138 | H112: =SUM(H108:H111) -> -3166.4312 | I112: =SUM(I108:I111) -> -3293.4885 | J112: =SUM(J108:J111) -> -3435.5385 | ... M112: =SUM(M108:M111) -> -3837.8568
B114: Financing Activities
B115: Proceeds from (Repayments) of Short-Term Debt: | C115: -974 | D115: 1035 | E115: -1035 | F115: 0 | G115: =G232+G233 -> 0 | H115: =H232+H233 -> 0 | I115: =I232+I233 -> 0 | J115: =J232+J233 -> 0 | K115: =K232+K233 -> 0 | L115: =L232+L233 -> 0 | M115: =M232+M233 -> 0
B116: Proceeds of Long-Term Debt, Net of Discounts and Premiums: | C116: 7933 | D116: 2979 | E116: 6942 | F116: 1995 | G116: =G256+G257 -> -1100 | H116: =H256+H257 -> -2750 | I116: =I256+I257 -> -3050 | J116: =J256+J257 -> -2500 | K116: =K256+K257 -> -2500 | L116: =L256+L257 -> -2500 | M116: =M256+M257 -> -2500
B117: Repayments of Long-Term Debt: | C117: -2872 | D117: -1532 | E117: -2491 | F117: -1271 | G117: =G256+G257 -> -1100 | H117: =H256+H257 -> -2750 | I117: =I256+I257 -> -3050 | J117: =J256+J257 -> -2500 | K117: =K256+K257 -> -2500 | L117: =L256+L257 -> -2500 | M117: =M256+M257 -> -2500
B118: Operating Lease ROU Assets (Repayments) | G118: =G224+G225 -> 0 | H118: =H224+H225 -> 0 | I118: =I224+I225 -> 0 | J118: =J224+J225 -> 0 | K118: =K224+K225 -> 0 | L118: =L224+L225 -> 0 | M118: =M224+M225 -> 0
...

Sheet Quarterly Model
B3: Home Depot (NYSE: HD)
B4: Quarterly Financial Model
B5: Financial Statements & Supporting Schedules
B7: Period End: | C7: =DATE(2020,5,3) -> 43954 | D7: =DATE(2020,8,2) -> 44045 | E7: =DATE(2020,11,1) -> 44136 | F7: =DATE(2021,1,31) -> 44227 | G7: =DATE(2021,1,31) -> 44227 | H7: =DATE(2021,5,2) -> 44318 | I7: =DATE(2021,8,1) -> 44409 | J7: =DATE(2021,10,31) -> 44500 | K7: =DATE(2022,1,30) -> 44591 | L7: =DATE(2022,1,30) -> 44591 | M7: =DATE(2022,5,1) -> 44682 | N7: =DATE(2022,7,31) -> 44773 | O7: =DATE(2022,10,30) -> 44864 | P7: =DATE(2022,1,29) -> 44590 | Q7: =DATE(2022,1,29) -> 44590 | R7: =DATE(2023,4,30) -> 45046 | S7: =DATE(2023,7,30) -> 45137 | T7: =DATE(2023,10,29) -> 45228 | U7: =DATE(2024,1,28) -> 45319 | V7: =DATE(2024,1,28) -> 45319 | W7: =DATE(2024,4,28) -> 45410 | X7: =DATE(2024,7,28) -> 45501 | Y7: =DATE(2024,10,27) -> 45592
B8: USD millions (expect per share data) | C8: Q1-2020 | D8: Q2-2020 | E8: Q3-2020 | F8: Q4-2020 | G8: FY2020 | H8: Q1-2021 | I8: Q2-2021 | J8: Q3-2021 | K8: Q4-2021 | L8: FY2021 | M8: Q1-2022 | N8: Q2-2022 | O8: Q3-2022 | P8: Q4-2022 | Q8: FY2022 | R8: Q1-2023 | S8: Q2-2023 | T8: Q3-2023 | U8: Q4-2023 | V8: FY2023 | W8: Q1-2024 | X8: Q2-2024 | Y8: Q3-2024 | Z8: Q4-2024E | AA8: FY2024E | AB8: Q1-2025E | AC8: Q2-2025E | AD8: Q3-2025E | AE8: Q4-2025E | AF8: FY2025E | AG8: Q1-2026E | AH8: Q2-2026E | AI8: Q3-2026E | AJ8: Q4-2026E | AK8: FY2026E | AL8: FY2027E | AM8: FY2028E | AN8: FY2029E | AO8: FY2030E
B11: Income Statement
B12: Revenue | C12: 28260 | D12: 38053 | E12: 33536 | F12: =G12-C12-D12-E12 -> 32261 | G12: 132110 | H12: 37500 | I12: 41118 | J12: 36820 | K12: =L12-H12-I12-J12 -> 35719 | L12: 151157 | M12: 38908 | N12: 43792 | O12: 38872 | P12: =Q12-M12-N12-O12 -> 35831 | Q12: 157403 | R12: 37257 | S12: 42916 | T12: 37710 | U12: =V12-R12-S12-T12 -> 34786 | V12: 152669 | W12: 36418 | X12: 43175 | Y12: 40217
B13: y/y growth % | H13: =H12/C12-1 -> 0.32696391 | I13: =I12/D12-1 -> 0.080545555 | J13: =J12/E12-1 -> 0.097924618 | K13: =K12/F12-1 -> 0.10718825 | L13: =L12/G12-1 -> 0.14417531 | M13: =M12/H12-1 -> 0.037546667 | N13: =N12/I12-1 -> 0.065032346 | O13: =O12/J12-1 -> 0.055730581 | ... Y13: =Y12/T12-1 -> 0.06648104
B14: Cost of Sales | C14: 18635 | D14: 25112 | E14: 22080 | F14: =G14-C14-D14-E14 -> 21430 | G14: 87257 | H14: 24758 | I14: 27453 | J14: 24257 | K14: =L14-H14-I14-J14 -> 23857 | L14: 100325 | M14: 25763 | N14: 29309 | O14: 25648 | P14: =Q14-M14-N14-O14 -> 23905 | Q14: 104625 | R14: 24700 | S14: 28759 | T14: 24972 | U14: =V14-R14-S14-T14 -> 23278 | V14: 101709 | W14: 23985 | X14: 28759 | Y14: 26792
B15: COGS % Rev | G15: =G14/G12 -> 0.66048747 | H15: =H14/H12 -> 0.66021333 | I15: =I14/I12 -> 0.6676638 | J15: =J14/J12 -> 0.65879957 | K15: =K14/K12 -> 0.66790784 | L15: =L14/L12 -> 0.66371389 | M15: =M14/M12 -> 0.66215174 | N15: =N14/N12 -> 0.66927749 | ... Y15: =Y14/Y12 -> 0.66618594
B16: Gross Profit | C16: =C12-C14 -> 9625 | D16: =D12-D14 -> 12941 | E16: =E12-E14 -> 11456 | F16: =G16-C16-D16-E16 -> 10831 | G16: =G12-G14 -> 44853 | H16: =H12-H14 -> 12742 | I16: =I12-I14 -> 13665 | J16: =J12-J14 -> 12563 | K16: =L16-H16-I16-J16 -> 11862 | L16: =L12-L14 -> 50832 | M16: =M12-M14 -> 13145 | N16: =N12-N14 -> 14483 | O16: =O12-O14 -> 13224 | P16: =Q16-M16-N16-O16 -> 11926 | Q16: =Q12-Q14 -> 52778 | R16: =R12-R14 -> 12557 | S16: =S12-S14 -> 14157 | T16: =T12-T14 -> 12738 | U16: =U12-U14 -> 11508 | V16: =V12-V14 -> 50960 | W16: =W12-W14 -> 12433 | X16: =X12-X14 -> 14416 | Y16: =Y12-Y14 -> 13425
B17: Operating Expenses
B18: Selling, General, and Administrative: | C18: 5829 | D18: 6355 | E18: 6076 | F18: =G18-C18-D18-E18 -> 6187 | G18: 24447 | H18: 6374 | I18: 6433 | J18: 6168 | K18: =L18-H18-I18-J18 -> 6431 | L18: 25406 | M18: 6610 | N18: 6657 | O18: 6468 | P18: =Q18-M18-N18-O18 -> 6549 | Q18: 26284 | R18: 6355 | S18: 6915 | T18: 6649 | U18: =V18-R18-S18-T18 -> 6679 | V18: 26598 | W18: 6667 | X18: 7144 | Y18: 7212
B19: SG&A % Rev | G19: =G18/G12 -> 0.18505034 | L19: =L18/L12 -> 0.1680769 | Q19: =Q18/Q12 -> 0.16698538 | V19: =V18/V12 -> 0.17422004
B20: EBITDA | C20: =C23+C21 -> 3796 | D20: =D23+D21 -> 6586 | E20: =E23+E21 -> 5380 | F20: =F23+F21 -> 4644 | G20: =G23+G21 -> 20406 | H20: =H23+H21 -> 6368 | I20: =I23+I21 -> 7232 | J20: =J23+J21 -> 6395 | K20: =L20-H20-I20-J20 -> 5431 | L20: =L23+L21 -> 25426 | M20: =M23+M21 -> 6535 | N20: =N23+N21 -> 7826 | O20: =O23+O21 -> 6756 | P20: =P23+P21 -> 5377 | Q20: =Q23+Q21 -> 26494 | R20: =R23+R21 -> 6202 | S20: =S23+S21 -> 7242 | ... Y20: =Y23+Y21 -> 6213
B21: Depreciation and Amortization | C21: 520 | D21: 519 | E21: 528 | F21: =G21-C21-D21-E21 -> 561 | G21: 2128 | H21: 587 | I21: 593 | J21: 600 | K21: =L21-H21-I21-J21 -> 606 | L21: 2386 | M21: 606 | N21: 616 | O21: 608 | P21: =Q21-M21-N21-O21 -> 625 | Q21: 2455 | R21: 651 | S21: 653 | T21: 683 | U21: =V21-R21-S21-T21 -> 686 | V21: 2673 | W21: 687 | X21: 738 | Y21: 795
B22: Depreciation % Revenue: | C22: =C21/C12 -> 0.018400566 | D22: =D21/D12 -> 0.013638872 | E22: =E21/E12 -> 0.015744275 | F22: =F21/F12 -> 0.017389418 | G22: =G21/G12 -> 0.016107789 | H22: =H21/H12 -> 0.015653333 | I22: =I21/I12 -> 0.014421908 | J22: =J21/J12 -> 0.016295492 | ... Y22: =Y21/Y12 -> 0.01976776
B23: EBIT | C23: =C16-C18-C21 -> 3276 | D23: =D16-D18-D21 -> 6067 | E23: =E16-E18-E21 -> 4852 | F23: =F16-F18-F21 -> 4083 | G23: =G16-G18-G21 -> 18278 | H23: =H16-H18-H21 -> 5781 | I23: =I16-I18-I21 -> 6639 | J23: =J16-J18-J21 -> 5795 | K23: =L23-H23-I23-J23 -> 4825 | L23: =L16-L18-L21 -> 23040 | M23: =M16-M18-M21 -> 5929 | N23: =N16-N18-N21 -> 7210 | O23: =O16-O18-O21 -> 6148 | P23: =P16-P18-P21 -> 4752 | Q23: =Q16-Q18-Q21 -> 24039 | R23: =R16-R18-R21 -> 5551 | S23: =S16-S18-S21 -> 6589 | ... Y23: =Y16-Y18-Y21 -> 5418
B24: Interest & Other (Income) Expense
B25: Interest and Investment Income: | C25: -17 | D25: -9 | E25: -11 | F25: =G25-C25-D25-E25 -> -10 | G25: -47 | H25: -6 | I25: -5 | J25: -15 | K25: =L25-H25-I25-J25 -> -18 | L25: -44 | M25: -3 | N25: -2 | O25: -7 | P25: =Q25-M25-N25-O25 -> -43 | Q25: -55 | R25: -33 | S25: -41 | T25: -49 | U25: =V25-R25-S25-T25 -> -55 | V25: -178 | W25: -57 | X25: -84 | Y25: -30
B26: Interest Expense: | C26: 324 | D26: 346 | E26: 340 | F26: =G26-C26-D26-E26 -> 337 | G26: 1347 | H26: 339 | I26: 326 | J26: 341 | K26: =L26-H26-I26-J26 -> 341 | L26: 1347 | M26: 372 | N26: 381 | O26: 413 | P26: =Q26-M26-N26-O26 -> 451 | Q26: 1617 | R26: 474 | S26: 469 | T26: 487 | U26: =V26-R26-S26-T26 -> 513 | V26: 1943 | W26: 485 | X26: 573 | Y26: 625
B27: Net Interest & Other | C27: =SUM(C25:C26) -> 307 | D27: =SUM(D25:D26) -> 337 | E27: =SUM(E25:E26) -> 329 | F27: =SUM(F25:F26) -> 327 | G27: =SUM(G25:G26) -> 1300 | H27: =SUM(H25:H26) -> 333 | I27: =SUM(I25:I26) -> 321 | J27: =SUM(J25:J26) -> 326 | ... Y27: =SUM(Y25:Y26) -> 595
B28: EBT | C28: =C23-C27 -> 2969 | D28: =D23-D27 -> 5730 | E28: =E23-E27 -> 4523 | F28: =F23-F27 -> 3756 | G28: =G23-G27 -> 16978 | H28: =H23-H27 -> 5448 | I28: =I23-I27 -> 6318 | J28: =J23-J27 -> 5469 | ... Y28: =Y23-Y27 -> 4823
B29: Provision for Income Taxes | C29: 724 | D29: 1398 | E29: 1091 | F29: =G29-C29-D29-E29 -> 899 | G29: 4112 | H29: 1303 | I29: 1511 | J29: 1340 | K29: =L29-H29-I29-J29 -> 1150 | L29: 5304 | M29: 1329 | N29: 1658 | O29: 1403 | P29: =Q29-M29-N29-O29 -> 982 | Q29: 5372 | R29: 1237 | S29: 1502 | T29: 1158 | U29: =V29-R29-S29-T29 -> 884 | V29: 4781 | W29: 1051 | X29: 1484 | Y29: 1175
B30: Income Tax Expense (%): | C30: =C29/C28 -> 0.24385315 | D30: =D29/D28 -> 0.24397906 | E30: =E29/E28 -> 0.24121159 | F30: =F29/F28 -> 0.23935037 | G30: =G29/G28 -> 0.24219578 | H30: =H29/H28 -> 0.23917034 | I30: =I29/I28 -> 0.23915796 | J30: =J29/J28 -> 0.24501737 | ... Y30: =Y29/Y28 -> 0.2436243
B31: Net Earnings (Net Income) | C31: =C28-C29 -> 2245 | D31: =D28-D29 -> 4332 | E31: =E28-E29 -> 3432 | F31: =F28-F29 -> 2857 | G31: =G28-G29 -> 12866 | H31: =H28-H29 -> 4145 | I31: =I28-I29 -> 4807 | J31: =J28-J29 -> 4129 | ... Y31: =Y28-Y29 -> 3648
B32: Earnings Per Share
B33: Basic EPS | C33: 2.09 | D33: 4.04 | E33: 3.2 | F33: =G33-C33-D33-E33 -> 2.65 | G33: 11.98 | H33: 3.87 | I33: 4.54 | J33: 3.94 | K33: =L33-H33-I33-J33 -> 3.24 | L33: 15.59 | M33: 4.11 | N33: 5.06 | O33: 4.25 | P33: =Q33-M33-N33-O33 -> 3.32 | Q33: 16.74 | R33: 3.83 | S33: 4.66 | T33: 3.83 | U33: =V33-R33-S33-T33 -> 2.84 | V33: 15.16 | W33: 3.64 | X33: 4.61 | Y33: 3.68
B34: Diluted EPS | C34: 2.08 | D34: 4.02 | E34: 3.18 | F34: =G34-C34-D34-E34 -> 2.66 | G34: 11.94 | H34: 3.86 | I34: 4.53 | J34: 3.92 | K34: =L34-H34-I34-J34 -> 3.22 | L34: 15.53 | M34: 4.09 | N34: 5.05 | O34: 4.24 | P34: =Q34-M34-N34-O34 -> 3.31 | Q34: 16.69 | R34: 3.82 | S34: 4.65 | T34: 3.81 | U34: =V34-R34-S34-T34 -> 2.83 | V34: 15.11 | W34: 3.63 | X34: 4.6 | Y34: 3.67
B35: Shares Used in Computing EPS
B36: Basic Weighted Average Common Shares | C36: 1073 | D36: 1073 | E36: 1073 | F36: 1074 | G36: 1074 | H36: 1071 | I36: 1058 | J36: 1049 | K36: 1054 | L36: 1054 | M36: 1030 | N36: 1023 | O36: 1020 | P36: 1022 | Q36: 1022 | R36: 1010 | S36: 1000 | T36: 996 | U36: 999 | V36: 999 | W36: 989 | X36: 990 | Y36: 991
B37: Diluted Weighted Average Common Shares | C37: 1077 | D37: 1077 | E37: 1078 | F37: 1078 | G37: 1078 | H37: 1075 | I37: 1062 | J37: 1053 | K37: 1058 | L37: 1058 | M37: 1034 | N37: 1025 | O37: 1023 | P37: 1025 | Q37: 1025 | R37: 1013 | S37: 1003 | T37: 999 | U37: 1002 | V37: 1002 | W37: 992 | X37: 992 | Y37: 993
B42: Balance Sheet
B43: Assets
B44: Cash & Cash Equivalents: | C44: 8696 | D44: 14139 | E44: 14652 | F44: 7895 | G44: 7895 | H44: 6648 | I44: 4566 | J44: 5067 | K44: 2343 | L44: 2343 | M44: 2844 | N44: 1259 | O44: 2462 | P44: 2757 | Q44: 2757 | R44: 1260 | S44: 2814 | T44: 2058 | U44: 3760 | V44: 3760 | W44: 4264 | X44: 1613 | Y44: 1531
B45: Receivables, Net: | C45: 2610 | D45: 2562 | E45: 2666 | F45: 2992 | G45: 2992 | H45: 3624 | I45: 3322 | J45: 3533 | K45: 3426 | L45: 3426 | M45: 3936 | N45: 3725 | O45: 3732 | P45: 3317 | Q45: 3317 | R45: 4213 | S45: 3836 | T45: 3932 | U45: 3328 | V45: 3328 | W45: 4105 | X45: 5503 | Y45: 5782
B46: Merchandise Inventories: | C46: 14989 | D46: 13498 | E46: 16155 | F46: 16627 | G46: 16627 | H46: 19178 | I46: 18909 | J46: 20582 | K46: 22068 | L46: 22068 | M46: 25297 | N46: 26088 | O46: 25719 | P46: 24886 | Q46: 24886 | R46: 25371 | S46: 23265 | T46: 22805 | U46: 20976 | V46: 20976 | W46: 22416 | X46: 23060 | Y46: 23897
B47: Other Current Assets: | C47: 982 | D47: 1162 | E47: 1032 | F47: 963 | G47: 963 | H47: 1222 | I47: 1465 | J47: 1284 | K47: 1218 | L47: 1218 | M47: 1790 | N47: 1869 | O47: 1768 | P47: 1511 | Q47: 1511 | R47: 1579 | S47: 1915 | T47: 1887 | U47: 1711 | V47: 1711 | W47: 1837 | X47: 2097 | Y47: 1739
B48: Total Current Assets | C48: =SUM(C44:C47) -> 27277 | D48: =SUM(D44:D47) -> 31361 | E48: =SUM(E44:E47) -> 34505 | F48: =SUM(F44:F47) -> 28477 | G48: =SUM(G44:G47) -> 28477 | H48: =SUM(H44:H47) -> 30672 | I48: =SUM(I44:I47) -> 28262 | J48: =SUM(J44:J47) -> 30466 | ... Y48: =SUM(Y44:Y47) -> 32949
B50: Net Property & Equipment | C50: 22697 | D50: 23387 | E50: 23848 | F50: 24705 | G50: 24705 | H50: 24673 | I50: 24750 | J50: 24935 | K50: 25199 | L50: 25199 | M50: 25166 | N50: 25247 | O50: 25240 | P50: 25631 | Q50: 25631 | R50: 25674 | S50: 25879 | T50: 25735 | U50: 26154 | V50: 26154 | W50: 25997 | X50: 26640 | Y50: 26573
B51: Operating Lease ROU Assets | C51: 5634 | D51: 5436 | E51: 5433 | F51: 5962 | G51: 5962 | H51: 5864 | I51: 5960 | J51: 5903 | K51: 5968 | L51: 5968 | M51: 5980 | N51: 6132 | O51: 6523 | P51: 6941 | Q51: 6941 | R51: 6931 | S51: 7139 | T51: 7071 | U51: 7884 | V51: 7884 | W51: 7913 | X51: 8613 | Y51: 8521
B52: Goodwill | C52: 2220 | D52: 2233 | E52: 2236 | F52: 7126 | G52: 7126 | H52: 7137 | I52: 7454 | J52: 7445 | K52: 7449 | L52: 7449 | M52: 7450 | N52: 7451 | O52: 7434 | P52: 7444 | Q52: 7444 | R52: 7447 | S52: 7664 | T52: 7937 | U52: 8455 | V52: 8455 | W52: 8464 | X52: 19414 | Y52: 19428
B53: Intangible Assets: | X53: 9214 | Y53: 9112
B54: Other Assets | C54: 909 | D54: 932 | E54: 897 | F54: 4311 | G54: 4311 | H54: 4221 | I54: 4343 | J54: 4282 | K54: 4205 | L54: 4205 | M54: 4104 | N54: 4054 | O54: 3988 | P54: 3958 | Q54: 3958 | R54: 3911 | S54: 3875 | T54: 4152 | U54: 4262 | V54: 4262 | W54: 4234 | X54: 692 | Y54: 681
B55: Total Non-Current Assets | C55: =SUM(C50:C54) -> 31460 | D55: =SUM(D50:D54) -> 31988 | E55: =SUM(E50:E54) -> 32414 | F55: =SUM(F50:F54) -> 42104 | G55: =SUM(G50:G54) -> 42104 | H55: =SUM(H50:H54) -> 41895 | I55: =SUM(I50:I54) -> 42507 | J55: =SUM(J50:J54) -> 42565 | ... Y55: =SUM(Y50:Y54) -> 64315
B56: Total Assets | C56: =C48+C55 -> 58737 | D56: =D48+D55 -> 63349 | E56: =E48+E55 -> 66919 | F56: =F48+F55 -> 70581 | G56: =G48+G55 -> 70581 | H56: =H48+H55 -> 72567 | I56: =I48+I55 -> 70769 | J56: =J48+J55 -> 73031 | ... Y56: =Y48+Y55 -> 97264
B58: Liabilities & Stockholders' Equity
B59: Short-Term Debt: | C59: 0 | D59: 0 | E59: 0 | F59: 0 | G59: 0 | K59: 1035 | L59: 1035 | N59: 539 | W59: 8 | X59: 2527 | Y59: 1344
B60: Accounts Payable: | C60: 10056 | D60: 11691 | E60: 12899 | F60: 11606 | G60: 11606 | H60: 14494 | I60: 12817 | J60: 13375 | K60: 13462 | L60: 13462 | M60: 15367 | N60: 14348 | O60: 12402 | P60: 11443 | Q60: 11443 | R60: 12630 | S60: 12104 | T60: 11478 | U60: 10037 | V60: 10037 | W60: 12563 | X60: 13206 | Y60: 13506
B61: Accrued Salaries and Related Expenses: | C61: 1974 | D61: 2402 | E61: 2176 | F61: 2463 | G61: 2463 | H61: 2167 | I61: 2329 | J61: 2028 | K61: 2426 | L61: 2426 | M61: 2008 | N61: 2204 | O61: 1934 | P61: 1991 | Q61: 1991 | R61: 1931 | S61: 2022 | T61: 2034 | U61: 2096 | V61: 2096 | W61: 2005 | X61: 2105 | Y61: 2094
B62: Sales Taxes Payable: | C62: 855 | D62: 907 | E62: 861 | F62: 774 | G62: 774 | H62: 1149 | I62: 1014 | J62: 968 | K62: 848 | L62: 848 | M62: 1139 | N62: 1076 | O62: 640 | P62: 528 | Q62: 528 | R62: 683 | S62: 631 | T62: 590 | U62: 449 | V62: 449 | W62: 676 | X62: 645 | Y62: 655
B63: Deferred Revenue: | C63: 2179 | D63: 2511 | E63: 2664 | F63: 2823 | G63: 2823 | H63: 3415 | I63: 3498 | J63: 3499 | K63: 3596 | L63: 3596 | M63: 3675 | N63: 3539 | O63: 3173 | P63: 3064 | Q63: 3064 | R63: 3119 | S63: 3079 | T63: 2784 | U63: 2762 | V63: 2762 | W63: 2841 | X63: 2754 | Y63: 2595
B64: Income Taxes Payable | F64: 193 | G64: 193 | K64: 158 | L64: 158 | P64: 50 | Q64: 50 | R64: 1054 | S64: 19 | T64: 304 | U64: 28 | V64: 28 | W64: 637 | X64: 40 | Y64: 94
B65: Current Installments of Long-Term Debt: | C65: 4200 | D65: 2476 | E65: 2491 | F65: 1416 | G65: 1416 | H65: 1164 | I65: 2428 | J65: 2436 | K65: 2447 | L65: 2447 | M65: 2463 | N65: 1218 | O65: 1224 | P65: 1231 | Q65: 1231 | R65: 1338 | S65: 1352 | T65: 1362 | U65: 1368 | V65: 1368 | W65: 763 | X65: 1339 | Y65: 3176
B66: Current Operating Lease Liabilities: | C66: 853 | D66: 831 | E66: 842 | F66: 828 | G66: 828 | H66: 803 | I66: 814 | J66: 827 | K66: 830 | L66: 830 | M66: 859 | N66: 919 | O66: 942 | P66: 945 | Q66: 945 | R66: 966 | S66: 1011 | T66: 1026 | U66: 1050 | V66: 1050 | W66: 1073 | X66: 1242 | Y66: 1262
B67: Other Accrued Expenses: | C67: 3231 | D67: 3381 | E67: 3462 | F67: 3063 | G67: 3063 | H67: 4566 | I67: 3766 | J67: 3770 | K67: 3891 | L67: 3891 | M67: 4876 | N67: 3991 | O67: 3965 | P67: 3858 | Q67: 3858 | R67: 3725 | S67: 4009 | T67: 3994 | U67: 4225 | V67: 4225 | W67: 3793 | X67: 4265 | Y67: 4366
B68: Total Current Liabilities | C68: =SUM(C59:C67) -> 23348 | D68: =SUM(D59:D67) -> 24199 | E68: =SUM(E59:E67) -> 25395 | F68: =SUM(F59:F67) -> 23166 | G68: =SUM(G59:G67) -> 23166 | H68: =SUM(H59:H67) -> 27758 | I68: =SUM(I59:I67) -> 26666 | J68: =SUM(J59:J67) -> 26903 | ... Y68: =SUM(Y59:Y67) -> 29092
B70: Long-Term Debt, Excluding Current Installments: | C70: 31622 | D70: 32370 | E70: 32831 | F70: 35822 | G70: 35822 | H70: 34697 | I70: 33746 | J70: 36712 | K70: 36604 | L70: 36604 | M70: 39158 | N70: 39271 | O70: 41740 | P70: 41962 | Q70: 41962 | R70: 40915 | S70: 40754 | T70: 40567 | U70: 42743 | V70: 42743 | W70: 42060 | X70: 51869 | Y70: 50058
B71: Long-Term Operating Lease Liabilities: | C71: 5075 | D71: 4895 | E71: 4880 | F71: 5356 | G71: 5356 | H71: 5279 | I71: 5360 | J71: 5290 | K71: 5353 | L71: 5353 | M71: 5335 | N71: 5431 | O71: 5807 | P71: 6226 | Q71: 6226 | R71: 6209 | S71: 6376 | T71: 6300 | U71: 7082 | V71: 7082 | W71: 7107 | X71: 7635 | Y71: 7538
B72: Deferred Income Taxes: | F72: 1131 | G72: 1131 | K72: 909 | L72: 909 | P72: 1019 | Q72: 1019 | R72: 954 | S72: 956 | T72: 753 | U72: 863 | V72: 863 | W72: 946 | X72: 2074 | Y72: 2083
B73: Other Long-Term Liabilities: | C73: 2182 | D73: 2299 | E73: 2278 | F73: 1807 | G73: 1807 | H73: 3085 | I73: 2928 | J73: 3091 | K73: 2013 | L73: 2013 | M73: 3396 | N73: 3052 | O73: 3741 | P73: 2566 | Q73: 2566 | R73: 2500 | S73: 2739 | T73: 2955 | U73: 2783 | V73: 2783 | W73: 2938 | X73: 2725 | Y73: 2707
B74: Total Non-Current Liabilities | C74: =SUM(C70:C73) -> 38879 | D74: =SUM(D70:D73) -> 39564 | E74: =SUM(E70:E73) -> 39989 | F74: =SUM(F70:F73) -> 44116 | G74: =SUM(G70:G73) -> 44116 | H74: =SUM(H70:H73) -> 43061 | I74: =SUM(I70:I73) -> 42034 | J74: =SUM(J70:J73) -> 45093 | ... Y74: =SUM(Y70:Y73) -> 62386
B75: Total Liabilities | C75: =C68+C74 -> 62227 | D75: =D68+D74 -> 63763 | E75: =E68+E74 -> 65384 | F75: =F68+F74 -> 67282 | G75: =G68+G74 -> 67282 | H75: =H68+H74 -> 70819 | I75: =I68+I74 -> 68700 | J75: =J68+J74 -> 71996 | ... Y75: =Y68+Y74 -> 91478
B77: Stockholders' Equity
B78: Common Stock: | C78: 89 | D78: 89 | E78: 89 | F78: 89 | G78: 89 | H78: 90 | I78: 90 | J78: 90 | K78: 90 | L78: 90 | M78: 90 | N78: 90 | O78: 90 | P78: 90 | Q78: 90 | R78: 90 | S78: 90 | T78: 90 | U78: 90 | V78: 90 | W78: 90 | X78: 90 | Y78: 90
B79: Paid-in Capital: | C79: 11008 | D79: 11228 | E79: 11312 | F79: 11540 | G79: 11540 | H79: 11555 | I79: 11797 | J79: 11889 | K79: 12132 | L79: 12132 | M79: 12079 | N79: 12309 | O79: 12385 | P79: 12592 | Q79: 12592 | R79: 12584 | S79: 12842 | T79: 12927 | U79: 13147 | V79: 13147 | W79: 13153 | X79: 13731 | Y79: 13835
B80: Retained Earnings: | C80: 52354 | D80: 55074 | E80: 56892 | F80: 58134 | G80: 58134 | H80: 60504 | I80: 63560 | J80: 65951 | K80: 67580 | L80: 67580 | M80: 69849 | N80: 73074 | O80: 75467 | P80: 76896 | Q80: 76896 | R80: 78651 | S80: 81213 | T80: 82934 | U80: 83656 | V80: 83656 | W80: 85027 | X80: 87357 | Y80: 88771
B81: Accumulated Other Comprehensive (Income) Loss: | C81: -1148 | D81: -1012 | E81: -965 | F81: -671 | G81: -671 | H81: -608 | I81: -585 | J81: -602 | K81: -704 | L81: -704 | M81: -683 | N81: -672 | O81: -856 | P81: -718 | Q81: -718 | R81: -637 | S81: -467 | T81: -662 | U81: -477 | V81: -477 | W81: -478 | X81: -787 | Y81: -939
B82: Treasury Stock | C82: -65793 | D82: -65793 | E82: -65793 | F82: -65793 | G82: -65793 | H82: -69793 | I82: -72793 | J82: -76293 | K82: -80794 | L82: -80794 | M82: -83044 | N82: -84564 | O82: -85788 | P82: -87298 | Q82: -87298 | R82: -90326 | S82: -92343 | T82: -93859 | U82: -95372 | V82: -95372 | W82: -95972 | X82: -95971 | Y82: -95971
B83: Total Stockholders' Equity (Deficit) | C83: =SUM(C78:C82) -> -3490 | D83: =SUM(D78:D82) -> -414 | E83: =SUM(E78:E82) -> 1535 | F83: =SUM(F78:F82) -> 3299 | G83: =SUM(G78:G82) -> 3299 | H83: =SUM(H78:H82) -> 1748 | I83: =SUM(I78:I82) -> 2069 | J83: =SUM(J78:J82) -> 1035 | ... Y83: =SUM(Y78:Y82) -> 5786
B84: Total Liabilties & Stockholders' Equity | C84: =C75+C83 -> 58737 | D84: =D75+D83 -> 63349 | E84: =E75+E83 -> 66919 | F84: =F75+F83 -> 70581 | G84: =G75+G83 -> 70581 | H84: =H75+H83 -> 72567 | I84: =I75+I83 -> 70769 | J84: =J75+J83 -> 73031 | ... Y84: =Y75+Y83 -> 97264
B86: Balance Check: | C86: =IF(C56=C84,("Y"), ("N")) -> Y | E86: =IF(E56=E84,("Y"), ("N")) -> Y | F86: =IF(F56=F84,("Y"), ("N")) -> Y | G86: =IF(G56=G84,("Y"), ("N")) -> Y | H86: =IF(H56=H84,("Y"), ("N")) -> Y | I86: =IF(I56=I84,("Y"), ("N")) -> Y | J86: =IF(J56=J84,("Y"), ("N")) -> Y | K86: =IF(K56=K84,("Y"), ("N")) -> Y | L86: =IF(L56=L84,("Y"), ("N")) -> Y | ... Y86: =IF(Y56=Y84,("Y"), ("N")) -> Y
B90: Cash Flow Statement
B91: Operating Activities
B92: Net Earnings (Net Income): | C92: 2245 | D92: =6577-2245 -> 4332 | E92: =10009-D92-C92 -> 3432 | F92: =G92-C92-D92-E92 -> 2857 | G92: 12866 | H92: 4145 | I92: =8952-4145 -> 4807 | J92: =13081-I92-H92 -> 4129 | K92: =L92-H92-I92-J92 -> 3352 | L92: 16433 | M92: 4231 | N92: =9404-M92 -> 5173 | O92: =13743-N92-M92 -> 4339 | P92: =Q92-M92-N92-O92 -> 3362 | Q92: 17105 | R92: 3873 | S92: =8532-R92 -> 4659 | T92: =12342-S92-R92 -> 3810 | U92: =V92-T92-S92-R92 -> 2801 | V92: 15143 | W92: 3600 | X92: =8161-W92 -> 4561 | Y92: =11809-X92-W92 -> 3648
B93: Depreciation & Amortization: | C93: 607 | D93: =1222-607 -> 615 | E93: =1853-D93-C93 -> 631 | F93: =G93-C93-D93-E93 -> 666 | G93: 2519 | H93: 703 | I93: =1414-703 -> 711 | J93: =2128-I93-H93 -> 714 | K93: =L93-H93-I93-J93 -> 734 | L93: 2862 | M93: 727 | N93: =1473-M93 -> 746 | O93: =2216-N93-M93 -> 743 | P93: =Q93-M93-N93-O93 -> 759 | Q93: 2975 | R93: 793 | S93: =1588-R93 -> 795 | T93: =2415-S93-R93 -> 827 | U93: =V93-T93-S93-R93 -> 832 | V93: 3247 | W93: 837 | X93: =1615-W93 -> 778 | Y93: =2472-X93-W93 -> 857
B94: Intangible Asset Amortization: | X94: =142-W94 -> 142 | Y94: =280-X94 -> 138
B95: Stock-Based Compensation Expense: | C95: 88 | D95: =155-88 -> 67 | E95: =234-D95-C95 -> 79 | F95: =G95-C95-D95-E95 -> 76 | G95: 310 | H95: 146 | I95: =226-146 -> 80 | J95: =312-I95-H95 -> 86 | K95: =L95-H95-I95-J95 -> 87 | L95: 399 | M95: 115 | N95: =196-M95 -> 81 | O95: =286-N95-M95 -> 90 | P95: =Q95-M95-N95-O95 -> 80 | Q95: 366 | R95: 124 | S95: =215-R95 -> 91 | T95: =300-S95-R95 -> 85 | U95: =V95-T95-S95-R95 -> 80 | V95: 380 | W95: 124 | X95: =222-W95 -> 98 | Y95: =328-X95-W95 -> 106
B96: Impairment Loss: | G96: 0
B97: Changes in Receivables, Net: | C97: -534 | D97: =(-477)-(-534) -> 57 | E97: =(-580)-D97-C97 -> -103 | F97: =G97-C97-D97-E97 -> 115 | G97: -465 | H97: -640 | I97: =-321-H97 -> 319 | J97: =-533-I97-H97 -> -212 | K97: =L97-H97-I97-J97 -> 98 | L97: -435 | M97: -489 | N97: =-295-M97 -> 194 | O97: =-312-N97-M97 -> -17 | P97: =Q97-M97-N97-O97 -> 423 | Q97: 111 | R97: -893 | S97: =-492-R97 -> 401 | T97: =-538-S97-R97 -> -46 | U97: =V97-T97-S97-R97 -> 672 | V97: 134 | W97: -795 | X97: =-391-W97 -> 404 | Y97: =-668-X97-W97 -> -277
B98: Changes in Merchandise Inventories: | C98: -633 | D98: =920-(-633) -> 1553 | E98: =(-1718)-D98-C98 -> -2638 | F98: =G98-C98-D98-E98 -> 61 | G98: -1657 | H98: -2519 | I98: =-2191-H98 -> 328 | J98: =-3871-I98-H98 -> -1680 | K98: =L98-H98-I98-J98 -> -1532 | L98: -5403 | M98: -3226 | N98: =-4009-M98 -> -783 | O98: =-3748-N98-M98 -> 261 | P98: =Q98-M98-N98-O98 -> 918 | Q98: -2830 | R98: -457 | S98: =1751-R98 -> 2208 | T98: =2131-S98-R98 -> 380 | U98: =V98-T98-S98-R98 -> 2006 | V98: 4137 | W98: -1452 | X98: =-214-W98 -> 1238 | Y98: =-1111-X98-W98 -> -897
B99: Changes in Other Current Assets: | C99: 62 | D99: =(-126)-62 -> -188 | E99: =12-D99-C99 -> 138 | F99: =G99-C99-D99-E99 -> 31 | G99: 43 | H99: -277 | I99: =-574-H99 -> -297 | J99: =-375-I99-H99 -> 199 | K99: =L99-H99-I99-J99 -> 45 | L99: -330 | M99: -589 | N99: =-668-M99 -> -79 | O99: =-568-N99-M99 -> 100 | P99: =Q99-M99-N99-O99 -> 257 | Q99: -311 | R99: -60 | S99: =-392-R99 -> -332 | T99: =-365-S99-R99 -> 27 | U99: =V99-T99-S99-R99 -> 181 | V99: -184 | W99: -113 | X99: =-339-W99 -> -226 | Y99: =19-X99-W99 -> 358
B100: Changes in Accounts Payable & Accrued Expenses: | C100: 3274 | D100: =5673-3274 -> 2399 | E100: =6555-D100-C100 -> 882 | F100: =G100-C100-D100-E100 -> -1437 | G100: 5118 | H100: 3013 | I100: =1658-H100 -> -1355 | J100: =1918-I100-H100 -> 260 | K100: =L100-H100-I100-J100 -> 483 | L100: 2401 | M100: 1744 | N100: =1079-M100 -> -665 | O100: =-1568-N100-M100 -> -2647 | P100: =Q100-M100-N100-O100 -> -1009 | Q100: -2577 | R100: 1158 | S100: =929-R100 -> -229 | T100: =187-S100-R100 -> -742 | U100: =V100-T100-S100-R100 -> -1598 | V100: -1411 | W100: 2511 | X100: =1628-W100 -> -883 | Y100: =1963-X100-W100 -> 335
B101: Changes in Deferred Revenue: | C101: 71 | D101: =397-71 -> 326 | E101: =549-D101-C101 -> 152 | F101: =G101-C101-D101-E101 -> 153 | G101: 702 | H101: 586 | I101: =671-H101 -> 85 | J101: =672-I101-H101 -> 1 | K101: =L101-H101-I101-J101 -> 103 | L101: 775 | M101: 79 | N101: =-57-M101 -> -136 | O101: =-413-N101-M101 -> -356 | P101: =Q101-M101-N101-O101 -> -113 | Q101: -526 | R101: 57 | S101: =10-R101 -> -47 | T101: =-276-S101-R101 -> -286 | U101: =V101-T101-S101-R101 -> -42 | V101: -318 | W101: 81 | X101: =-31-W101 -> -112 | Y101: =-188-X101-W101 -> -157
B102: Changes in Income Taxes Payable: | C102: 594 | D102: =447-594 -> -147 | E102: =530-D102-C102 -> 83 | F102: =G102-C102-D102-E102 -> -679 | G102: -149 | H102: 1138 | I102: =154-H102 -> -984 | J102: =-10-I102-H102 -> -164 | K102: =L102-H102-I102-J102 -> -41 | L102: -51 | M102: 1121 | N102: =61-M102 -> -1060 | O102: =30-N102-M102 -> -31 | P102: =Q102-M102-N102-O102 -> -137 | Q102: -107 | R102: 1004 | S102: =-32-R102 -> -1036 | T102: =252-S102-R102 -> 284 | U102: =V102-T102-S102-R102 -> -277 | V102: -25 | W102: 610 | X102: =14-W102 -> -596 | Y102: =69-X102-W102 -> 55
B103: Changes in Deferred Income Taxes: | C103: -68 | D103: =13-(-68) -> 81 | E103: =(-86)-D103-C103 -> -99 | F103: =G103-C103-D103-E103 -> -483 | G103: -569 | H103: -87 | I103: =-116-H103 -> -29 | J103: =-73-I103-H103 -> 43 | K103: =L103-H103-I103-J103 -> -203 | L103: -276 | M103: -44 | N103: =-95-M103 -> -51 | O103: =129-N103-M103 -> 224 | P103: =Q103-M103-N103-O103 -> 9 | Q103: 138 | R103: -59 | S103: =-48-R103 -> 11 | T103: =-310-S103-R103 -> -262 | U103: =V103-T103-S103-R103 -> 65 | V103: -245 | W103: 83 | X103: =159-W103 -> 76 | Y103: =170-X103-W103 -> 11
B104: Other Operating Activities: | C104: 31 | D104: =28-31 -> -3 | E104: =57-D104-C104 -> 29 | F104: =G104-C104-D104-E104 -> 64 | G104: 121 | H104: 102 | I104: =74-H104 -> -28 | J104: =137-I104-H104 -> 63 | K104: =L104-H104-I104-J104 -> 59 | L104: 196 | M104: 120 | N104: =93-M104 -> -27 | O104: =226-N104-M104 -> 133 | P104: =Q104-M104-N104-O104 -> 45 | Q104: 271 | R104: 74 | S104: =144-R104 -> 70 | T104: =301-S104-R104 -> 157 | U104: =V104-T104-S104-R104 -> 13 | V104: 314 | W104: 11 | X104: =-60-W104 -> -71 | Y104: =-4-X104-W104 -> 56
B105: Cash Flow From Operating Activities | C105: =SUM(C92:C104) -> 5737 | D105: =SUM(D92:D104) -> 9092 | E105: =SUM(E92:E104) -> 2586 | F105: =SUM(F92:F104) -> 1424 | G105: =SUM(G92:G104) -> 18839 | H105: =SUM(H92:H104) -> 6310 | I105: =SUM(I92:I104) -> 3637 | J105: =SUM(J92:J104) -> 3439 | ... Y105: =SUM(Y92:Y104) -> 4233
B107: Investing Activities
B108: Capital Expenditures: | C108: -586 | D108: =(-1032)-(-586) -> -446 | E108: =(-1503)-D108-C108 -> -471 | F108: =G108-C108-D108-E108 -> -960 | G108: -2463 | H108: -524 | I108: =-1042-H108 -> -518 | J108: =-1737-I108-H108 -> -695 | K108: =L108-H108-I108-J108 -> -829 | L108: -2566 | M108: -704 | N108: =-1447-M108 -> -743 | O108: =-2216-N108-M108 -> -769 | P108: =Q108-M108-N108-O108 -> -903 | Q108: -3119 | R108: -905 | S108: =-1697-R108 -> -792 | T108: =-2368-S108-R108 -> -671 | U108: =V108-T108-S108-R108 -> -858 | V108: -3226 | W108: -847 | X108: =-1566-W108 -> -719 | Y108: =-2384-X108-W108 -> -818
B109: Payments for Businesses Acquired: | F109: -7780 | G109: -7780 | I109: -416 | J109: =-416-I109-H109 -> 0 | K109: =L109-H109-I109-J109 -> -5 | L109: -421 | S109: -215 | T109: =-795-S109-R109 -> -580 | U109: =V109-T109-S109-R109 -> -719 | V109: -1514 | X109: =-17570-W109 -> -17570 | Y109: =-17613-X109-W109 -> -43
B110: Proceeds from Sales of Property and Equipment: | C110: 8 | D110: =12-8 -> 4 | E110: =55-D110-C110 -> 43 | F110: =G110-C110-D110-E110 -> -55
B111: Other Investing Activities: | C111: 0 | D111: =0-0 -> 0 | E111: =(-3)-D111-C111 -> -3 | F111: =G111-C111-D111-E111 -> 76 | G111: 73 | H111: -4 | I111: =0-H111 -> 4 | J111: =21-I111-H111 -> 21 | K111: =L111-H111-I111-J111 -> -3 | L111: 18 | M111: 3 | N111: =-14-M111 -> -17 | O111: =-29-N111-M111 -> -15 | P111: =Q111-M111-N111-O111 -> 8 | Q111: -21 | R111: 2 | S111: =10-R111 -> 8 | T111: =15-S111-R111 -> 5 | U111: =V111-T111-S111-R111 -> -4 | V111: 11 | W111: 17 | X111: =38-W111 -> 21 | Y111: =85-X111-W111 -> 47
B112: Cash Flow from Investing Activities | C112: =SUM(C108:C111) -> -578 | D112: =SUM(D108:D111) -> -442 | E112: =SUM(E108:E111) -> -431 | F112: =SUM(F108:F111) -> -8719 | G112: =SUM(G108:G111) -> -10170 | H112: =SUM(H108:H111) -> -528 | I112: =SUM(I108:I111) -> -930 | J112: =SUM(J108:J111) -> -674 | ... Y112: =SUM(Y108:Y111) -> -814
B114: Financing Activities
B115: Proceeds from (Repayments) of Short-Term Debt: | C115: -974 | D115: =(-974)-(-974) -> 0 | E115: =(-974)-D115-C115 -> 0 | F115: =G115-C115-D115-E115 -> 0 | G115: -974 | K115: =L115-H115-I115-J115 -> 1035 | L115: 1035 | M115: -1035 | N115: =-496-M115 -> 539 | O115: =-1035-N115-M115 -> -539 | P115: =Q115-M115-N115-O115 -> 0 | Q115: -1035 | W115: 8 | X115: =2527-W115 -> 2519 | Y115: =1344-X115-W115 -> -1183
B116: Proceeds of Long-Term Debt, Net of Discounts and Premiums: | C116: 4960 | D116: =4960-4960 -> 0 | E116: =4960-D116-C116 -> 0 | F116: =G116-C116-D116-E116 -> 2973 | G116: 7933 | J116: =2979-I116-H116 -> 2979 | K116: =L116-H116-I116-J116 -> 0 | L116: 2979 | M116: 3957 | N116: =3957-M116 -> 0 | O116: =6942-N116-M116 -> 2985 | P116: =Q116-M116-N116-O116 -> 0 | Q116: 6942 | U116: =V116-T116-S116-R116 -> 1995 | V116: 1995 | X116: =9952-W116 -> 9952 | Y116: =9983-X116-W116 -> 31
B117: Repayments of Long-Term Debt: | C117: -27 | D117: =(-1806)-(-27) -> -1779 | E117: =(-1836)-D117-C117 -> -30 | F117: =G117-C117-D117-E117 -> -1036 | G117: -2872 | H117: -1390 | I117: =-1434-H117 -> -44 | J117: =-1480-I117-H117 -> -46 | K117: =L117-H117-I117-J117 -> -52 | L117: -1532 | M117: -1054 | N117: =-2366-M117 -> -1312 | O117: =-2423-N117-M117 -> -57 | P117: =Q117-M117-N117-O117 -> -68 | Q117: -2491 | R117: -1063 | S117: =-1130-R117 -> -67 | T117: =-1200-S117-R117 -> -70 | U117: =V117-T117-S117-R117 -> -71 | V117: -1271 | W117: -1172 | X117: =-1255-W117 -> -83 | Y117: =-1355-X117-W117 -> -100
B118: Repurchases of Common Stock: | C118: -791 | D118: =(-791)-(-791) -> 0 | E118: =(-791)-D118-C118 -> 0 | F118: =G118-C118-D118-E118 -> 0 | G118: -791 | H118: -3788 | I118: =-6905-H118 -> -3117 | J118: =-10374-I118-H118 -> -3469 | K118: =L118-H118-I118-J118 -> -4435 | L118: -14809 | M118: -2308 | N118: =-3962-M118 -> -1654 | O118: =-5136-N118-M118 -> -1174 | P118: =Q118-M118-N118-O118 -> -1560 | Q118: -6696 | R118: -2887 | S118: =-4954-R118 -> -2067 | T118: =-6465-S118-R118 -> -1511 | U118: =V118-T118-S118-R118 -> -1486 | V118: -7951 | W118: -649 | X118: =-649-W118 -> 0 | Y118: =-649-X118-W118 -> 0
B119: Proceeds from Sales of Common Stock: | C119: 18 | D119: =164-18 -> 146 | E119: =185-D119-C119 -> 21 | F119: =G119-C119-D119-E119 -> 141 | G119: 326 | H119: 13 | I119: =167-H119 -> 154 | J119: =190-I119-H119 -> 23 | K119: =L119-H119-I119-J119 -> 147 | L119: 337 | M119: 5 | N119: =142-M119 -> 137 | O119: =146-N119-M119 -> 4 | P119: =Q119-M119-N119-O119 -> 118 | Q119: 264 | R119: 15 | S119: =175-R119 -> 160 | T119: =192-S119-R119 -> 17 | U119: =V119-T119-S119-R119 -> 131 | V119: 323 | W119: 62 | X119: =210-W119 -> 148 | Y119: =231-X119-W119 -> 21
...

Sheet Key Metrics
B1: Home Depot (NYSE: HD)
B2: Key Financial Ratios
B5: Period End: | C5: =DATE(2021,1,31) -> 44227 | D5: =DATE(2022,1,30) -> 44591 | E5: =DATE(2022,1,29) -> 44590 | F5: =DATE(2024,1,28) -> 45319
B6: USD millions (expect per share data) | C6: FY2021A | D6: FY2022A | E6: FY2023A | F6: FY2024A | G6: FY2025E | H6: FY2026E | I6: FY2027E | J6: FY2028E | K6: FY2029E | L6: FY2030E | M6: FY2031E
B9: Liquidity Ratios
B10: Current Ratio | C10: ='Annual Model'!C42/'Annual Model'!C63 -> 1.0780952 | D10: ='Annual Model'!D42/'Annual Model'!D63 -> 1.2292584 | E10: ='Annual Model'!E42/'Annual Model'!E63 -> 1.0126163 | F10: ='Annual Model'!F42/'Annual Model'!F63 -> 1.4050627 | G10: ='Annual Model'!G42/'Annual Model'!G63 -> 1.4391967 | H10: ='Annual Model'!H42/'Annual Model'!H63 -> 1.3799911 | I10: ='Annual Model'!I42/'Annual Model'!I63 -> 1.3169967 | J10: ='Annual Model'!J42/'Annual Model'!J63 -> 1.3146028 | ... M10: ='Annual Model'!M42/'Annual Model'!M63 -> 1.4247132
B11: Acid-Test Ratio | C11: =('Annual Model'!C42-'Annual Model'!C40)/'Annual Model'!C63 -> 0.28729252 | D11: =('Annual Model'!D42-'Annual Model'!D40)/'Annual Model'!D63 -> 0.51152551 | E11: =('Annual Model'!E42-'Annual Model'!E40)/'Annual Model'!E63 -> 0.24350887 | F11: =('Annual Model'!F42-'Annual Model'!F40)/'Annual Model'!F63 -> 0.32821289 | G11: =('Annual Model'!G42-'Annual Model'!G40)/'Annual Model'!G63 -> 0.50176159 | H11: =('Annual Model'!H42-'Annual Model'!H40)/'Annual Model'!H63 -> 0.45411265 | I11: =('Annual Model'!I42-'Annual Model'!I40)/'Annual Model'!I63 -> 0.39870184 | J11: =('Annual Model'!J42-'Annual Model'!J40)/'Annual Model'!J63 -> 0.40243697 | ... M11: =('Annual Model'!M42-'Annual Model'!M40)/'Annual Model'!M63 -> 0.5340101
B12: Cash Ratio | C12: ='Annual Model'!C38/'Annual Model'!C63 -> 0.11608163 | D12: ='Annual Model'!D38/'Annual Model'!D63 -> 0.34080117 | E12: ='Annual Model'!E38/'Annual Model'!E63 -> 0.081657547 | F12: ='Annual Model'!F38/'Annual Model'!F63 -> 0.119299 | G12: ='Annual Model'!G38/'Annual Model'!G63 -> 0.31271589 | H12: ='Annual Model'!H38/'Annual Model'!H63 -> 0.2741009 | I12: ='Annual Model'!I38/'Annual Model'!I63 -> 0.22686363 | J12: ='Annual Model'!J38/'Annual Model'!J63 -> 0.23805683 | ... M12: ='Annual Model'!M38/'Annual Model'!M63 -> 0.38917153
B13: Leverage Ratios
B14: Debt Ratio | C14: ='Annual Model'!C70/'Annual Model'!C50 -> 1.0608166 | D14: ='Annual Model'!D70/'Annual Model'!D50 -> 0.95325938 | E14: ='Annual Model'!E70/'Annual Model'!E50 -> 1.0235962 | F14: ='Annual Model'!F70/'Annual Model'!F50 -> 0.97956701 | G14: ='Annual Model'!G70/'Annual Model'!G50 -> 0.94791752 | H14: ='Annual Model'!H70/'Annual Model'!H50 -> 0.91021745 | I14: ='Annual Model'!I70/'Annual Model'!I50 -> 0.86491634 | J14: ='Annual Model'!J70/'Annual Model'!J50 -> 0.81484795 | ... M14: ='Annual Model'!M70/'Annual Model'!M50 -> 0.63825261
B15: D/E Ratio | C15: ='Annual Model'!C70/'Annual Model'!C79 -> 1.0608166 | D15: ='Annual Model'!D70/'Annual Model'!D79 -> 0.95325938 | E15: ='Annual Model'!E70/'Annual Model'!E79 -> 1.0235962 | F15: ='Annual Model'!F70/'Annual Model'!F79 -> 0.97956701 | G15: ='Annual Model'!G70/'Annual Model'!G79 -> 0.94791752 | H15: ='Annual Model'!H70/'Annual Model'!H79 -> 0.91021745 | I15: ='Annual Model'!I70/'Annual Model'!I79 -> 0.86491634 | J15: ='Annual Model'!J70/'Annual Model'!J79 -> 0.81484795 | ... M15: ='Annual Model'!M70/'Annual Model'!M79 -> 0.63825261
B16: Profitability Ratios
B17: ROA | C17: ='Annual Model'!C25/'Annual Model'!C50 -> 0.2511125 | D17: ='Annual Model'!D25/'Annual Model'!D50 -> 0.2328247 | E17: ='Annual Model'!E25/'Annual Model'!E50 -> 0.2379793 | F17: ='Annual Model'!F25/'Annual Model'!F50 -> 0.19809013 | G17: ='Annual Model'!G25/'Annual Model'!G50 -> 0.19066488 | H17: ='Annual Model'!H25/'Annual Model'!H50 -> 0.19842128 | I17: ='Annual Model'!I25/'Annual Model'!I50 -> 0.20891859 | J17: ='Annual Model'!J25/'Annual Model'!J50 -> 0.21593757 | ... M17: ='Annual Model'!M25/'Annual Model'!M50 -> 0.2247823
B18: ROE | C18: ='Annual Model'!C25/'Annual Model'!C78 -> -4.1290116 | D18: ='Annual Model'!D25/'Annual Model'!D78 -> 4.9812064 | E18: ='Annual Model'!E25/'Annual Model'!E78 -> -10.085495 | F18: ='Annual Model'!F25/'Annual Model'!F78 -> 9.6946223 | G18: ='Annual Model'!G25/'Annual Model'!G78 -> 3.6608257 | H18: ='Annual Model'!H25/'Annual Model'!H78 -> 2.2100206 | I18: ='Annual Model'!I25/'Annual Model'!I78 -> 1.5465867 | J18: ='Annual Model'!J25/'Annual Model'!J78 -> 1.1662716 | ... M18: ='Annual Model'!M25/'Annual Model'!M78 -> 0.62137918
B21: Cash Flow Ratios/Metrics
B22: FCF
B23: FCF | C23: ='Annual Model'!C105+'Annual Model'!C108 -> 16376 | D23: ='Annual Model'!D105+'Annual Model'!D108 -> 14005 | E23: ='Annual Model'!E105+'Annual Model'!E108 -> 11496 | F23: ='Annual Model'!F105+'Annual Model'!F108 -> 17946 | G23: ='Annual Model'!G105+'Annual Model'!G108 -> 19650.859 | H23: ='Annual Model'!H105+'Annual Model'!H108 -> 17240.631 | I23: ='Annual Model'!I105+'Annual Model'!I108 -> 17692.088 | J23: ='Annual Model'!J105+'Annual Model'!J108 -> 18322.039 | ... M23: ='Annual Model'!M105+'Annual Model'!M108 -> 20561.738
B24: FCF Growth % | D24: =D23/C23-1 -> -0.14478505 | E24: =E23/D23-1 -> -0.1791503 | F24: =F23/E23-1 -> 0.56106472 | G24: =G23/F23-1 -> 0.094999386 | H24: =H23/G23-1 -> -0.12265253 | I24: =I23/H23-1 -> 0.026185643 | J24: =J23/I23-1 -> 0.035606334 | K24: =K23/J23-1 -> 0.038609587 | ... M24: =M23/L23-1 -> 0.041407859
B26: UFCF
B27: EBIT | C27: ='Annual Model'!C17 -> 18278 | D27: ='Annual Model'!D17 -> 23040 | E27: ='Annual Model'!E17 -> 24039 | F27: ='Annual Model'!F17 -> 21689 | G27: ='Annual Model'!G17 -> 22075.783 | H27: ='Annual Model'!H17 -> 22579.235 | I27: ='Annual Model'!I17 -> 23317.23 | J27: ='Annual Model'!J17 -> 24147.594 | ... M27: ='Annual Model'!M17 -> 26390.009
B28: Operating Lease Interest Element | C28: 0 | D28: 0 | E28: 0 | F28: 0 | G28: 0 | H28: 0 | I28: 0 | J28: 0 | K28: 0 | L28: 0 | M28: 0
B29: Tax Rate | C29: ='Annual Model'!C24 -> 0.24219578 | D29: ='Annual Model'!D24 -> 0.24400791 | E29: ='Annual Model'!E24 -> 0.23899987 | F29: ='Annual Model'!F24 -> 0.23996186 | G29: ='Annual Model'!G24 -> 0.24 | H29: ='Annual Model'!H24 -> 0.24 | I29: ='Annual Model'!I24 -> 0.24 | J29: ='Annual Model'!J24 -> 0.24 | ... M29: ='Annual Model'!M24 -> 0.24
B30: NOPAT | C30: =C27*(1-C29) -> 13851.145 | D30: =D27*(1-D29) -> 17418.058 | E30: =E27*(1-E29) -> 18293.682 | F30: =F27*(1-F29) -> 16484.467 | G30: =G27*(1-G29) -> 16777.595 | H30: =H27*(1-H29) -> 17160.219 | I30: =I27*(1-I29) -> 17721.095 | J30: =J27*(1-J29) -> 18352.171 | ... M30: =M27*(1-M29) -> 20056.407
B31: D&A | C31: ='Annual Model'!C88 -> 2519 | D31: ='Annual Model'!D88 -> 2862 | E31: ='Annual Model'!E88 -> 2975 | F31: ='Annual Model'!F88 -> 3247 | G31: ='Annual Model'!G88 -> 3411.3957 | H31: ='Annual Model'!H88 -> 3570.2173 | I31: ='Annual Model'!I88 -> 3735.3917 | J31: ='Annual Model'!J88 -> 3907.6686 | ... M31: ='Annual Model'!M88 -> 4465.1162
B32: Deferred Income Taxes | C32: ='Annual Model'!C93 -> -569 | D32: ='Annual Model'!D93 -> -276 | E32: ='Annual Model'!E93 -> 138 | F32: ='Annual Model'!F93 -> -245 | G32: ='Annual Model'!G93 -> 678.81341 | H32: ='Annual Model'!H93 -> 688.53216 | I32: ='Annual Model'!I93 -> 497.61854 | J32: ='Annual Model'!J93 -> 341.98312 | ... M32: ='Annual Model'!M93 -> 117.08914
B33: Change in Working Capital | C33: ='Annual Model'!C103 -> 2847 | D33: ='Annual Model'!D103 -> -3488 | E33: ='Annual Model'!E103 -> -5403 | F33: ='Annual Model'!F103 -> 2835 | G33: ='Annual Model'!G103 -> 2655.6604 | H33: ='Annual Model'!H103 -> -361.41704 | I33: ='Annual Model'!I103 -> -492.01155 | J33: ='Annual Model'!J103 -> -549.87678 | ... M33: ='Annual Model'!M103 -> -510.7898
B34: CAPEX | C34: ='Annual Model'!C108 -> -2463 | D34: ='Annual Model'!D108 -> -2566 | E34: ='Annual Model'!E108 -> -3119 | F34: ='Annual Model'!F108 -> -3226 | G34: ='Annual Model'!G108 -> -3083.9138 | H34: ='Annual Model'!H108 -> -3176.4312 | I34: ='Annual Model'!I108 -> -3303.4885 | J34: ='Annual Model'!J108 -> -3445.5385 | ... M34: ='Annual Model'!M108 -> -3847.8568
B35: UFCF | C35: =SUM(C30:C34) -> 16185.145 | D35: =SUM(D30:D34) -> 13950.058 | E35: =SUM(E30:E34) -> 12884.682 | F35: =SUM(F30:F34) -> 19095.467 | G35: =SUM(G30:G34) -> 20439.551 | H35: =SUM(H30:H34) -> 17881.12 | I35: =SUM(I30:I34) -> 18158.605 | J35: =SUM(J30:J34) -> 18606.408 | ... M35: =SUM(M30:M34) -> 20279.966
B36: UFCF Margin % | C36: =C35/'Annual Model'!C10 -> 0.12251264 | D36: =D35/'Annual Model'!D10 -> 0.092288532 | E36: =E35/'Annual Model'!E10 -> 0.08185792 | F36: =F35/'Annual Model'!F10 -> 0.12507757 | G36: =G35/'Annual Model'!G10 -> 0.13255591 | H36: =H35/'Annual Model'!H10 -> 0.11258622 | I36: =I35/'Annual Model'!I10 -> 0.10993594 | J36: =J35/'Annual Model'!J10 -> 0.1080029 | ... M36: =M35/'Annual Model'!M10 -> 0.10540915
B38: LFCF
B39: Net Income | C39: ='Annual Model'!C25 -> 12866 | D39: ='Annual Model'!D25 -> 16433 | E39: ='Annual Model'!E25 -> 17105 | F39: ='Annual Model'!F25 -> 15143 | G39: ='Annual Model'!G25 -> 15201.47 | H39: ='Annual Model'!H25 -> 15671.39 | I39: ='Annual Model'!I25 -> 16331.91 | J39: ='Annual Model'!J25 -> 17063.092 | ... M39: ='Annual Model'!M25 -> 19079.233
B40: D&A | C40: ='Annual Model'!C88 -> 2519 | D40: ='Annual Model'!D88 -> 2862 | E40: ='Annual Model'!E88 -> 2975 | F40: ='Annual Model'!F88 -> 3247 | G40: ='Annual Model'!G88 -> 3411.3957 | H40: ='Annual Model'!H88 -> 3570.2173 | I40: ='Annual Model'!I88 -> 3735.3917 | J40: ='Annual Model'!J88 -> 3907.6686 | ... M40: ='Annual Model'!M88 -> 4465.1162
B41: Deferred Income Taxes | C41: ='Annual Model'!C93 -> -569 | D41: ='Annual Model'!D93 -> -276 | E41: ='Annual Model'!E93 -> 138 | F41: ='Annual Model'!F93 -> -245 | G41: ='Annual Model'!G93 -> 678.81341 | H41: ='Annual Model'!H93 -> 688.53216 | I41: ='Annual Model'!I93 -> 497.61854 | J41: ='Annual Model'!J93 -> 341.98312 | ... M41: ='Annual Model'!M93 -> 117.08914
B42: Change in Working Capital | C42: ='Annual Model'!C103 -> 2847 | D42: ='Annual Model'!D103 -> -3488 | E42: ='Annual Model'!E103 -> -5403 | F42: ='Annual Model'!F103 -> 2835 | G42: ='Annual Model'!G103 -> 2655.6604 | H42: ='Annual Model'!H103 -> -361.41704 | I42: ='Annual Model'!I103 -> -492.01155 | J42: ='Annual Model'!J103 -> -549.87678 | ... M42: ='Annual Model'!M103 -> -510.7898
B43: CAPEX | C43: ='Annual Model'!C108 -> -2463 | D43: ='Annual Model'!D108 -> -2566 | E43: ='Annual Model'!E108 -> -3119 | F43: ='Annual Model'!F108 -> -3226 | G43: ='Annual Model'!G108 -> -3083.9138 | H43: ='Annual Model'!H108 -> -3176.4312 | I43: ='Annual Model'!I108 -> -3303.4885 | J43: ='Annual Model'!J108 -> -3445.5385 | ... M43: ='Annual Model'!M108 -> -3847.8568
B44: Repayments of Debt Principal | C44: ='Annual Model'!C117 -> -2872 | D44: ='Annual Model'!D117 -> -1532 | E44: ='Annual Model'!E117 -> -2491 | F44: ='Annual Model'!F117 -> -1271 | G44: ='Annual Model'!G117 -> -1100 | H44: ='Annual Model'!H117 -> -2750 | I44: ='Annual Model'!I117 -> -3050 | J44: ='Annual Model'!J117 -> -2500 | ... M44: ='Annual Model'!M117 -> -2500
B45: New Debt Issuances | C45: 0 | D45: 0 | E45: 0 | F45: 0 | G45: 0 | H45: 0 | I45: 0 | J45: 0 | K45: 0 | L45: 0 | M45: 0
B46: LFCF | C46: =SUM(C39:C45) -> 12328 | D46: =SUM(D39:D45) -> 11433 | E46: =SUM(E39:E45) -> 9205 | F46: =SUM(F39:F45) -> 16483 | G46: =SUM(G39:G45) -> 17763.426 | H46: =SUM(H39:H45) -> 13642.291 | I46: =SUM(I39:I45) -> 13719.42 | J46: =SUM(J39:J45) -> 14817.328 | ... M46: =SUM(M39:M45) -> 16802.792
B47: LFCF Margin % | C47: =C46/'Annual Model'!C10 -> 0.093316176 | D47: =D46/'Annual Model'!D10 -> 0.07563659 | E47: =E46/'Annual Model'!E10 -> 0.058480461 | F47: =F46/'Annual Model'!F10 -> 0.1079656 | G47: =G46/'Annual Model'!G10 -> 0.11520054 | H47: =H46/'Annual Model'!H10 -> 0.085896973 | I47: =I46/'Annual Model'!I10 -> 0.083060195 | J47: =J46/'Annual Model'!J10 -> 0.086008781 | ... M47: =M46/'Annual Model'!M10 -> 0.087335848

Sheet DCF
B1: Home Depot (NYSE: HD)
B2: Discounted Cash Flow Analysis
B3: Sensitivity Tables
B5: Period End: | C5: =DATE(2021,1,31) -> 44227 | D5: =DATE(2022,1,30) -> 44591 | E5: =DATE(2022,1,29) -> 44590 | F5: =DATE(2024,1,28) -> 45319 | G5: Projections
B6: USD millions (expect per share data) | C6: FY2021A | D6: FY2022A | E6: FY2023A | F6: FY2024A | G6: FY2025E | H6: FY2026E | I6: FY2027E | J6: FY2028E | K6: FY2029E | L6: FY2030E | M6: FY2031E
B10: Discounted Cash Flow Analysis | P10: Gordon Growth Method | S10: Multiple Method
B11: Revenue | C11: ='Annual Model'!C10 -> 132110 | D11: ='Annual Model'!D10 -> 151157 | E11: ='Annual Model'!E10 -> 157403 | F11: ='Annual Model'!F10 -> 152669 | G11: ='Annual Model'!G10 -> 154195.69 | H11: ='Annual Model'!H10 -> 158821.56 | I11: ='Annual Model'!I10 -> 165174.42 | J11: ='Annual Model'!J10 -> 172276.92 | ... M11: ='Annual Model'!M10 -> 192392.84 | P11: Sum of PV UFCF | Q11: =SUM(G37:M37) -> 89503.912 | S11: Sum of PV UFCF | T11: =SUM(G37:M37) -> 89503.912
B12: % Growth | D12: =D11/C11-1 -> 0.14417531 | E12: =E11/D11-1 -> 0.041321275 | F12: =F11/E11-1 -> -0.030075666 | G12: =G11/F11-1 -> 0.01 | H12: =H11/G11-1 -> 0.03 | I12: =I11/H11-1 -> 0.04 | J12: =J11/I11-1 -> 0.043 | K12: =K11/J11-1 -> 0.04 | ... M12: =M11/L11-1 -> 0.035 | P12: Terminal Year UFCF | Q12: =M33 -> 18824.051 | S12: Exit Year EBITDA | T12: =M18 -> 29516.3
B13: Cost of Sales | C13: ='Annual Model'!C11 -> 87257 | D13: ='Annual Model'!D11 -> 100325 | E13: ='Annual Model'!E11 -> 104625 | F13: ='Annual Model'!F11 -> 101709 | G13: ='Annual Model'!G11 -> 102848.53 | H13: ='Annual Model'!H11 -> 106092.8 | I13: ='Annual Model'!I11 -> 110501.69 | J13: ='Annual Model'!J11 -> 115425.54 | ... M13: ='Annual Model'!M11 -> 129480.38 | P13: Perpetuity Growth Rate | Q13: 0.021 | S13: EBITDA Multiple | T13: =WACC!G21/DCF!T12 -> 15.21882
B14: Gross Margin % | C14: =C15/C11 -> 0.33951253 | D14: =D15/D11 -> 0.33628611 | E14: =E15/E11 -> 0.33530492 | F14: =F15/F11 -> 0.33379402 | G14: =G15/G11 -> 0.333 | H14: =H15/H11 -> 0.332 | I14: =I15/I11 -> 0.331 | J14: =J15/J11 -> 0.33 | ... M14: =M15/M11 -> 0.327 | P14: Terminal Value | Q14: =(Q12*(1+Q13)/(M35-Q13)) -> 290380.68 | S14: Terminal Value | T14: =T12*T13 -> 449203.26
B15: Gross Profit | C15: =C11-C13 -> 44853 | D15: =D11-D13 -> 50832 | E15: =E11-E13 -> 52778 | F15: =F11-F13 -> 50960 | G15: =G11-G13 -> 51347.165 | H15: =H11-H13 -> 52728.758 | I15: =I11-I13 -> 54672.734 | J15: =J11-J13 -> 56851.385 | ... M15: =M11-M13 -> 62912.458 | P15: PV of Terminal Value | Q15: =Q14/(1+M35)^M34 -> 161747.89 | S15: PV of Terminal Value | T15: =T14/(1+M35)^M34 -> 250215.27
B16: Selling, General, and Administrative: | C16: ='Annual Model'!C14 -> 24447 | D16: ='Annual Model'!D14 -> 25406 | E16: ='Annual Model'!E14 -> 26284 | F16: ='Annual Model'!F14 -> 26598 | G16: ='Annual Model'!G14 -> 26765.776 | H16: ='Annual Model'!H14 -> 27568.749 | I16: ='Annual Model'!I14 -> 28671.499 | J16: ='Annual Model'!J14 -> 29904.374 | ... M16: ='Annual Model'!M14 -> 33396.158 | P16: Enterprise Value | Q16: =Q15+Q11 -> 251251.81 | S16: Enterprise Value | T16: =T11+T15 -> 339719.19
B17: SG&A % Rev | C17: =C16/C11 -> 0.18505034 | D17: =D16/D11 -> 0.1680769 | E17: =E16/E11 -> 0.16698538 | F17: =F16/F11 -> 0.17422004 | G17: =G16/G11 -> 0.17358317 | H17: =H16/H11 -> 0.17358317 | I17: =I16/I11 -> 0.17358317 | J17: =J16/J11 -> 0.17358317 | ... M17: =M16/M11 -> 0.17358317 | P17: (+) Cash & Investments | Q17: 1531 | S17: (+) Cash & Investments | T17: 1531
B18: EBITDA | C18: =C22+C20 -> 20406 | D18: =D22+D20 -> 25426 | E18: =E22+E20 -> 26494 | F18: =F22+F20 -> 24362 | G18: =G22+G20 -> 24581.389 | H18: =H22+H20 -> 25160.009 | I18: =I22+I20 -> 26001.235 | J18: =J22+J20 -> 26947.011 | ... M18: =M22+M20 -> 29516.3 | P18: (+) Net Operating Losses | Q18: 99 | S18: (+) Net Operating Losses | T18: 99
B19: EBITDA Margin % | C19: =C18/C11 -> 0.15446219 | D19: =D18/D11 -> 0.16820921 | E19: =E18/E11 -> 0.16831954 | F19: =F18/F11 -> 0.15957398 | G19: =G18/G11 -> 0.15941683 | H19: =H18/H11 -> 0.15841683 | I19: =I18/I11 -> 0.15741683 | J19: =J18/J11 -> 0.15641683 | ... M19: =M18/M11 -> 0.15341683 | P19: (-) Total Debt & Finance Leases | Q19: -51402 | S19: (-) Total Debt & Finance Leases | T19: -51402
B20: Depreciation and Amortization | C20: ='Annual Model'!C16 -> 2128 | D20: ='Annual Model'!D16 -> 2386 | E20: ='Annual Model'!E16 -> 2455 | F20: ='Annual Model'!F16 -> 2673 | G20: ='Annual Model'!G16 -> 2505.6057 | H20: ='Annual Model'!H16 -> 2580.7739 | I20: ='Annual Model'!I16 -> 2684.0049 | J20: ='Annual Model'!J16 -> 2799.4171 | ... M20: ='Annual Model'!M16 -> 3126.291 | P20: (-) Preferred Stock | Q20: 0 | S20: (-) Preferred Stock | T20: 0
B21: D&A % Rev | C21: =C20/C11 -> 0.016107789 | D21: =D20/D11 -> 0.015784912 | E21: =E20/E11 -> 0.015596907 | F21: =F20/F11 -> 0.017508466 | G21: =G20/G11 -> 0.016249519 | H21: =H20/H11 -> 0.016249519 | I21: =I20/I11 -> 0.016249519 | J21: =J20/J11 -> 0.016249519 | ... M21: =M20/M11 -> 0.016249519 | P21: (-) Operating Leases | Q21: -8521 | S21: (-) Operating Leases | T21: -8521
B22: EBIT | C22: =C15-C16-C20 -> 18278 | D22: =D15-D16-D20 -> 23040 | E22: =E15-E16-E20 -> 24039 | F22: =F15-F16-F20 -> 21689 | G22: =G15-G16-G20 -> 22075.783 | H22: =H15-H16-H20 -> 22579.235 | I22: =I15-I16-I20 -> 23317.23 | J22: =J15-J16-J20 -> 24147.594 | ... M22: =M15-M16-M20 -> 26390.009 | P22: (-) Noncontrolling Interests | Q22: 0 | S22: (-) Noncontrolling Interests | T22: 0
B23: % Growth | D23: =D22/C22-1 -> 0.26053179 | E23: =E22/D22-1 -> 0.043359375 | F23: =F22/E22-1 -> -0.09775781 | G23: =G22/F22-1 -> 0.017833141 | H23: =H22/G22-1 -> 0.022805621 | I23: =I22/H22-1 -> 0.032684676 | J23: =J22/I22-1 -> 0.035611604 | K23: =K22/J22-1 -> 0.032580296 | ... M23: =M22/L22-1 -> 0.027509082 | P23: (-) Unfunded Pensions | Q23: 0 | S23: (-) Unfunded Pensions | T23: 0
B24: EBIT Margin % | C24: =C22/C11 -> 0.1383544 | D24: =D22/D11 -> 0.1524243 | E24: =E22/E11 -> 0.15272263 | F24: =F22/F11 -> 0.14206551 | G24: =G22/G11 -> 0.14316732 | H24: =H22/H11 -> 0.14216732 | I24: =I22/I11 -> 0.14116732 | J24: =J22/J11 -> 0.14016732 | ... M24: =M22/M11 -> 0.13716732 | P24: Implied Equity Value | Q24: =SUM(Q16:Q23) -> 192958.81 | S24: Implied Equity Value | T24: =SUM(T16:T23) -> 281426.19
B25: Income Tax Expense | C25: =-C22*'Annual Model'!C24 -> -4426.8545 | D25: =-D22*'Annual Model'!D24 -> -5621.9423 | E25: =-E22*'Annual Model'!E24 -> -5745.3178 | F25: =-F22*'Annual Model'!F24 -> -5204.5327 | G25: =-G22*'Annual Model'!G24 -> -5298.1879 | H25: =-H22*'Annual Model'!H24 -> -5419.0164 | I25: =-I22*'Annual Model'!I24 -> -5596.1352 | J25: =-J22*'Annual Model'!J24 -> -5795.4225 | ... M25: =-M22*'Annual Model'!M24 -> -6333.6022 | P25: Fully Diluted Shares Outstanding | Q25: ='Annual Model'!F31 -> 1002 | S25: Fully Diluted Shares Outstanding | T25: ='Annual Model'!F31 -> 1002
B26: Tax Rate % | C26: ='Annual Model'!C24 -> 0.24219578 | D26: ='Annual Model'!D24 -> 0.24400791 | E26: ='Annual Model'!E24 -> 0.23899987 | F26: ='Annual Model'!F24 -> 0.23996186 | G26: ='Annual Model'!G24 -> 0.24 | H26: ='Annual Model'!H24 -> 0.24 | I26: ='Annual Model'!I24 -> 0.24 | J26: ='Annual Model'!J24 -> 0.24 | ... M26: ='Annual Model'!M24 -> 0.24 | P26: Implied Share Price | Q26: =Q24/Q25 -> 192.57366 | S26: Implied Share Price | T26: =T24/T25 -> 280.86446
B27: NOPAT | C27: =C22+C25 -> 13851.145 | D27: =D22+D25 -> 17418.058 | E27: =E22+E25 -> 18293.682 | F27: =F22+F25 -> 16484.467 | G27: =G22+G25 -> 16777.595 | H27: =H22+H25 -> 17160.219 | I27: =I22+I25 -> 17721.095 | J27: =J22+J25 -> 18352.171 | ... M27: =M22+M25 -> 20056.407
B28: Add: D&A | C28: ='Annual Model'!C16 -> 2128 | D28: ='Annual Model'!D16 -> 2386 | E28: ='Annual Model'!E16 -> 2455 | F28: ='Annual Model'!F16 -> 2673 | G28: ='Annual Model'!G16 -> 2505.6057 | H28: ='Annual Model'!H16 -> 2580.7739 | I28: ='Annual Model'!I16 -> 2684.0049 | J28: ='Annual Model'!J16 -> 2799.4171 | ... M28: ='Annual Model'!M16 -> 3126.291 | P28: % EV from TV | Q28: =Q15/Q16 -> 0.64376809 | S28: % EV from TV | T28: =T15/T16 -> 0.7365356
B29: Less: CAPEX | C29: ='Annual Model'!C108 -> -2463 | D29: ='Annual Model'!D108 -> -2566 | E29: ='Annual Model'!E108 -> -3119 | F29: ='Annual Model'!F108 -> -3226 | G29: ='Annual Model'!G108 -> -3083.9138 | H29: ='Annual Model'!H108 -> -3176.4312 | I29: ='Annual Model'!I108 -> -3303.4885 | J29: ='Annual Model'!J108 -> -3445.5385 | ... M29: ='Annual Model'!M108 -> -3847.8568 | P29: Implied Multiple | Q29: =Q14/M18 -> 9.837977
B30: CAPEX % Rev | C30: =-C29/C11 -> 0.018643555 | D30: =-D29/D11 -> 0.016975727 | E30: =-E29/E11 -> 0.019815378 | F30: =-F29/F11 -> 0.021130681 | G30: =-G29/G11 -> 0.02 | H30: =-H29/H11 -> 0.02 | I30: =-I29/I11 -> 0.02 | J30: =-J29/J11 -> 0.02 | ... M30: =-M29/M11 -> 0.02
B31: Less: Change in Net Working Capital | C31: ='Annual Model'!C103 -> 2847 | D31: ='Annual Model'!D103 -> -3488 | E31: ='Annual Model'!E103 -> -5403 | F31: ='Annual Model'!F103 -> 2835 | G31: ='Annual Model'!G103 -> 2655.6604 | H31: ='Annual Model'!H103 -> -361.41704 | I31: ='Annual Model'!I103 -> -492.01155 | J31: ='Annual Model'!J103 -> -549.87678 | ... M31: ='Annual Model'!M103 -> -510.7898 | P31: Current Price | Q31: 390.13 | S31: Current Price | T31: 390.13
B32: Change in NWC % Rev | D32: =D31/D11 -> -0.023075346 | E32: =E31/E11 -> -0.034325902 | F32: =F31/F11 -> 0.018569585 | G32: =G31/G11 -> 0.017222663 | H32: =H31/H11 -> -0.002275617 | I32: =I31/I11 -> -0.0029787393 | J32: =J31/J11 -> -0.0031918192 | K32: =K31/K11 -> -0.0029928666 | ... M32: =M31/M11 -> -0.0026549315 | P32: Dividend Yield | Q32: 0.0231 | S32: Dividend Yield | T32: 0.0231
B33: UFCF | C33: =C27+C28+C29+C31 -> 16363.145 | D33: =D27+D28+D29+D31 -> 13750.058 | E33: =E27+E28+E29+E31 -> 12226.682 | F33: =F27+F28+F29+F31 -> 18766.467 | G33: =G27+G28+G29+G31 -> 18854.947 | H33: =H27+H28+H29+H31 -> 16203.144 | I33: =I27+I28+I29+I31 -> 16609.6 | J33: =J27+J28+J29+J31 -> 17156.173 | ... M33: =M27+M28+M29+M31 -> 18824.051 | P33: Implied Return | Q33: =((Q26-Q31)/Q31)+Q32 -> -0.48328592 | S33: Implied Return | T33: =((T26-T31)/T31)+T32 -> -0.2569747
B34: Discount Period | G34: 1 | H34: 2 | I34: 3 | J34: 4 | K34: 5 | L34: 6 | M34: 7
B35: WACC | G35: =WACC!D16 -> 0.08718676 | H35: =G35 -> 0.08718676 | I35: =H35 -> 0.08718676 | J35: =I35 -> 0.08718676 | K35: =J35 -> 0.08718676 | L35: =K35 -> 0.08718676 | M35: =L35 -> 0.08718676
B36: Discount Factor | G36: =1/(1+G35)^G34 -> 0.91980517 | H36: =1/(1+H35)^H34 -> 0.84604155 | I36: =1/(1+I35)^I34 -> 0.77819339 | J36: =1/(1+J35)^J34 -> 0.7157863 | K36: =1/(1+K35)^K34 -> 0.65838394 | L36: =1/(1+L35)^L34 -> 0.60558495 | M36: =1/(1+M35)^M34 -> 0.55702016
B37: PV of UFCF | G37: =G33*G36 -> 17342.878 | H37: =H33*H36 -> 13708.533 | I37: =I33*I36 -> 12925.481 | J37: =J33*J36 -> 12280.154 | K37: =K33*K36 -> 11680.981 | L37: =L33*L36 -> 11080.51 | M37: =M33*M36 -> 10485.376
B45: Sensitivity Tables
C46: WACC
C47: =$Q$26 -> 192.57366 | D47: 0.08 | E47: 0.0825 | F47: 0.085 | G47: 0.0875 | H47: 0.09 | I47: 0.0925 | J47: 0.095 | K47: 0.0975 | L47: 0.1 | M47: 0.1025
B48: Terminal UFCF Growth Rates | C48: 0.015 | D48: 192.57366 | E48: 192.57366 | F48: 192.57366 | G48: 192.57366 | H48: 192.57366 | I48: 192.57366 | J48: 192.57366 | K48: 192.57366 | L48: 192.57366 | M48: 192.57366
C49: 0.016 | D49: 192.57366 | E49: 192.57366 | F49: 192.57366 | G49: 192.57366 | H49: 192.57366 | I49: 192.57366 | J49: 192.57366 | K49: 192.57366 | L49: 192.57366 | M49: 192.57366
C50: 0.017 | D50: 192.57366 | E50: 192.57366 | F50: 192.57366 | G50: 192.57366 | H50: 192.57366 | I50: 192.57366 | J50: 192.57366 | K50: 192.57366 | L50: 192.57366 | M50: 192.57366
C51: 0.018 | D51: 192.57366 | E51: 192.57366 | F51: 192.57366 | G51: 192.57366 | H51: 192.57366 | I51: 192.57366 | J51: 192.57366 | K51: 192.57366 | L51: 192.57366 | M51: 192.57366
C52: 0.019 | D52: 192.57366 | E52: 192.57366 | F52: 192.57366 | G52: 192.57366 | H52: 192.57366 | I52: 192.57366 | J52: 192.57366 | K52: 192.57366 | L52: 192.57366 | M52: 192.57366
C53: 0.02 | D53: 192.57366 | E53: 192.57366 | F53: 192.57366 | G53: 192.57366 | H53: 192.57366 | I53: 192.57366 | J53: 192.57366 | K53: 192.57366 | L53: 192.57366 | M53: 192.57366
C54: 0.021 | D54: 192.57366 | E54: 192.57366 | F54: 192.57366 | G54: 192.57366 | H54: 192.57366 | I54: 192.57366 | J54: 192.57366 | K54: 192.57366 | L54: 192.57366 | M54: 192.57366
C55: 0.022 | D55: 192.57366 | E55: 192.57366 | F55: 192.57366 | G55: 192.57366 | H55: 192.57366 | I55: 192.57366 | J55: 192.57366 | K55: 192.57366 | L55: 192.57366 | M55: 192.57366
C56: 0.023 | D56: 192.57366 | E56: 192.57366 | F56: 192.57366 | G56: 192.57366 | H56: 192.57366 | I56: 192.57366 | J56: 192.57366 | K56: 192.57366 | L56: 192.57366 | M56: 192.57366
C57: 0.024 | D57: 192.57366 | E57: 192.57366 | F57: 192.57366 | G57: 192.57366 | H57: 192.57366 | I57: 192.57366 | J57: 192.57366 | K57: 192.57366 | L57: 192.57366 | M57: 192.57366
C61: Terminal EV / EBITDA Multiple
C62: =$T$26 -> 280.86446 | D62: 8.2 | E62: 8.4 | F62: 8.6 | G62: 8.8 | H62: 9 | I62: 9.2 | J62: 9.4 | K62: 9.6 | L62: 9.8 | M62: 10
B63: WACC | C63: 0.08 | D63: 280.86446 | E63: 280.86446 | F63: 280.86446 | G63: 280.86446 | H63: 280.86446 | I63: 280.86446 | J63: 280.86446 | K63: 280.86446 | L63: 280.86446 | M63: 280.86446
C64: 0.0825 | D64: 280.86446 | E64: 280.86446 | F64: 280.86446 | G64: 280.86446 | H64: 280.86446 | I64: 280.86446 | J64: 280.86446 | K64: 280.86446 | L64: 280.86446 | M64: 280.86446
C65: 0.085 | D65: 280.86446 | E65: 280.86446 | F65: 280.86446 | G65: 280.86446 | H65: 280.86446 | I65: 280.86446 | J65: 280.86446 | K65: 280.86446 | L65: 280.86446 | M65: 280.86446
C66: 0.0875 | D66: 280.86446 | E66: 280.86446 | F66: 280.86446 | G66: 280.86446 | H66: 280.86446 | I66: 280.86446 | J66: 280.86446 | K66: 280.86446 | L66: 280.86446 | M66: 280.86446
C67: 0.09 | D67: 280.86446 | E67: 280.86446 | F67: 280.86446 | G67: 280.86446 | H67: 280.86446 | I67: 280.86446 | J67: 280.86446 | K67: 280.86446 | L67: 280.86446 | M67: 280.86446
C68: 0.0925 | D68: 280.86446 | E68: 280.86446 | F68: 280.86446 | G68: 280.86446 | H68: 280.86446 | I68: 280.86446 | J68: 280.86446 | K68: 280.86446 | L68: 280.86446 | M68: 280.86446
C69: 0.095 | D69: 280.86446 | E69: 280.86446 | F69: 280.86446 | G69: 280.86446 | H69: 280.86446 | I69: 280.86446 | J69: 280.86446 | K69: 280.86446 | L69: 280.86446 | M69: 280.86446
C70: 0.0975 | D70: 280.86446 | E70: 280.86446 | F70: 280.86446 | G70: 280.86446 | H70: 280.86446 | I70: 280.86446 | J70: 280.86446 | K70: 280.86446 | L70: 280.86446 | M70: 280.86446
C71: 0.1 | D71: 280.86446 | E71: 280.86446 | F71: 280.86446 | G71: 280.86446 | H71: 280.86446 | I71: 280.86446 | J71: 280.86446 | K71: 280.86446 | L71: 280.86446 | M71: 280.86446
C72: 0.1025 | D72: 280.86446 | E72: 280.86446 | F72: 280.86446 | G72: 280.86446 | H72: 280.86446 | I72: 280.86446 | J72: 280.86446 | K72: 280.86446 | L72: 280.86446 | M72: 280.86446

Sheet WACC
C1: Home Depot (NYSE: HD)
C2: Weighted Average Cost of Capital (WACC)
C7: WACC Analysis | F7: Market Capitalization | I7: Capital Structure
C8: 30 Year US Treasury | D8: 0.0468 | F8: Share Price | G8: 390.13 | I8: Unit | J8: Value | K8: %
C9: Market Risk Premium | D9: 0.046 | F9: Shares Outstanding | G9: ='Annual Model'!F30 -> 999 | I9: Total Debt | J9: =50058+1344 -> 51402 | K9: =J9/J14 -> 0.89882493 | M9: Took most recent 10Q and added LT and ST debt
C10: Beta | D10: 1.01 | F10: Market Capitalization | G10: =G8*G9 -> 389739.87 | I10: Total Common Equity | J10: 5786 | K10: =J10/J14 -> 0.10117507 | M10: Took most recent 10Q value
C11: Cost of Equity | D11: =D8+(D9*D10) -> 0.09326 | F11: Diluted Shares Outstanding | G11: ='Annual Model'!F31 -> 1002 | I11: Total Preferred Equity | J11: 0 | K11: =J11/J14 -> 0
C12: % of Capital Structure | D12: =G13/(G13+J9) -> 0.88378798
C13: Cost of Debt | D13: 0.041 | F13: Diluted Market Capitalization | G13: =G8*G11 -> 390910.26 | I13: Total Noncontrolling Interests | J13: 0 | K13: =J13/J14 -> 0
C14: % of Capital Structure | D14: =J9/(G13+J9) -> 0.11621202 | F14: (-) Cash & Investments | G14: -1531 | H14: 10Q | I14: Total | J14: =SUM(J9:J13) -> 57188 | K14: =SUM(K9:K13) -> 1
F15: (-) Net Operating Losses | G15: -99
C16: WACC | D16: =(D11*D12)+(D13*D14) -> 0.08718676 | F16: (+) Total Debt & Finance Leases | G16: 51402
F17: (+) Preferred Stock | G17: 0
F18: (+) Operating Leases | G18: 8521 | H18: 10Q
F19: (+) Noncontrolling Interests | G19: 0
F20: (+) Unfunded Pensions | G20: 0
F21: Enterprise Value (TEV) | G21: =SUM(G13:G20) -> 449203.26

Sheet Comps
B1: Home Depot (NYSE: HD)
B2: Public Company Comparable Analysis
B4: Values in Million, Except Per Share Data
G9: Capitalization | N9: Revenue | Q9: EBITDA | T9: Net Income | W9: Growth Projections
B10: Company | C10: Ticker | D10: Share Price | E10: FDSO | F10: Market Cap | G10: Beta | H10: Tax Rate | I10: Cash | J10: Debt | K10: Preferred | L10: Other & NCI | M10: EV | N10: LTM | O10: 2025E | P10: 2026E | Q10: LTM | R10: 2025E | S10: 2026E | T10: LTM | U10: 2025E | V10: 2026E | W10: Revenue | X10: EBITDA
B11: Lowe's Companies | C11: LOW | D11: 248.66 | E11: 566 | F11: =D11*E11 -> 140741.56 | G11: 1.1 | H11: 0.2361 | I11: =-3271+622 -> -2649 | J11: =32759+622 -> 33381 | K11: 0 | L11: 0 | M11: =F11+I11+J11+K11+L11 -> 171473.56 | N11: 83722 | O11: 83330 | P11: 84670 | Q11: 12428 | R11: 12166 | S11: 12498 | T11: 6853 | U11: 7027 | V11: 7504 | W11: =P11/O11-1 -> 0.016080643 | X11: =S11/R11-1 -> 0.027289167
B12: Builders FirstSource | C12: BLDR | D12: 146.47 | E12: 116.9 | F12: =D12*E12 -> 17122.343 | G12: 2.08 | H12: 0.2381 | I12: -328 | J12: =3700+2.5 -> 3702.5 | K12: 0 | L12: 0 | M12: =F12+I12+J12+K12+L12 -> 20496.843 | N12: 16731 | O12: 17240 | P12: 18406 | Q12: 2349.1 | R12: 2314 | S12: 2586 | T12: 1238.3 | U12: 1142 | V12: 1344 | W12: =P12/O12-1 -> 0.067633411 | X12: =S12/R12-1 -> 0.11754538
B13: Floor & Décor | C13: FND | D13: 96.69 | E13: 108.3 | F13: =D13*E13 -> 10471.527 | G13: 1.75 | H13: 0.2183 | I13: -181 | J13: 201.6 | K13: 0 | L13: 0 | M13: =F13+I13+J13+K13+L13 -> 10492.127 | N13: 4396.5 | O13: 4850 | P13: 5510 | Q13: 470.7 | R13: 562.5 | S13: 669.4 | T13: 195.5 | U13: 212 | V13: 270.3 | W13: =P13/O13-1 -> 0.13608247 | X13: =S13/R13-1 -> 0.19004444
B14: Arhaus Inc | C14: ARHS | D14: 10.86 | E14: 140.7 | F14: =D14*E14 -> 1528.002 | G14: 2.5 | H14: 0.2309 | I14: -178 | K14: 36.4 | L14: 0 | M14: =F14+I14+J14+K14+L14 -> 1386.402 | N14: 1268 | O14: 1381 | P14: 1504 | Q14: 171.3 | R14: 156.8 | S14: 190.8 | T14: 78.5 | U14: 75.38 | V14: 98.17 | W14: =P14/O14-1 -> 0.089065894 | X14: =S14/R14-1 -> 0.21683673
B15: Haverty Furniture Companies Inc | C15: HVT | D15: 21.71 | E15: 16.8 | F15: =D15*E15 -> 364.728 | G15: 1.4 | H15: 0.2828 | I15: -121 | J15: 0 | K15: 0 | L15: 0 | M15: =F15+I15+J15+K15+L15 -> 243.728 | N15: 749.3 | O15: 764.3 | P15: 806.4 | Q15: 48.7 | R15: 69.19 | S15: 78 | T15: 26.8 | U15: 43.77 | V15: 52.15 | W15: =P15/O15-1 -> 0.055083083 | X15: =S15/R15-1 -> 0.12733054
B18: Maximum | D18: =MAX(D11:D15) -> 248.66 | F18: =MAX(F11:F15) -> 140741.56 | M18: =MAX(M11:M15) -> 171473.56 | N18: =MAX(N11:N15) -> 83722 | O18: =MAX(O11:O15) -> 83330 | P18: =MAX(P11:P15) -> 84670 | Q18: =MAX(Q11:Q15) -> 12428 | R18: =MAX(R11:R15) -> 12166 | S18: =MAX(S11:S15) -> 12498 | T18: =MAX(T11:T15) -> 6853 | ... X18: =MAX(X11:X15) -> 0.21683673
B19: 75th Percentile | D19: =_xlfn.QUARTILE.EXC(D11:D15,3) -> 197.565 | F19: =_xlfn.QUARTILE.EXC(F11:F15,3) -> 78931.951 | M19: =_xlfn.QUARTILE.EXC(M11:M15,3) -> 95985.201 | N19: =_xlfn.QUARTILE.EXC(N11:N15,3) -> 50226.5 | O19: =_xlfn.QUARTILE.EXC(O11:O15,3) -> 50285 | P19: =_xlfn.QUARTILE.EXC(P11:P15,3) -> 51538 | Q19: =_xlfn.QUARTILE.EXC(Q11:Q15,3) -> 7388.55 | R19: =_xlfn.QUARTILE.EXC(R11:R15,3) -> 7240 | S19: =_xlfn.QUARTILE.EXC(S11:S15,3) -> 7542 | T19: =_xlfn.QUARTILE.EXC(T11:T15,3) -> 4045.65 | ... X19: =_xlfn.QUARTILE.EXC(X11:X15,3) -> 0.20344059
B20: Median | D20: =MEDIAN(D11:D15) -> 96.69 | F20: =MEDIAN(F11:F15) -> 10471.527 | M20: =MEDIAN(M11:M15) -> 10492.127 | N20: =MEDIAN(N11:N15) -> 4396.5 | O20: =MEDIAN(O11:O15) -> 4850 | P20: =MEDIAN(P11:P15) -> 5510 | Q20: =MEDIAN(Q11:Q15) -> 470.7 | R20: =MEDIAN(R11:R15) -> 562.5 | S20: =MEDIAN(S11:S15) -> 669.4 | T20: =MEDIAN(T11:T15) -> 195.5 | ... X20: =MEDIAN(X11:X15) -> 0.12733054
B21: 25th Percentile | D21: =_xlfn.QUARTILE.EXC(D11:D15,1) -> 16.285 | F21: =_xlfn.QUARTILE.EXC(F11:F15,1) -> 946.365 | M21: =_xlfn.QUARTILE.EXC(M11:M15,1) -> 815.065 | N21: =_xlfn.QUARTILE.EXC(N11:N15,1) -> 1008.65 | O21: =_xlfn.QUARTILE.EXC(O11:O15,1) -> 1072.65 | P21: =_xlfn.QUARTILE.EXC(P11:P15,1) -> 1155.2 | Q21: =_xlfn.QUARTILE.EXC(Q11:Q15,1) -> 110 | R21: =_xlfn.QUARTILE.EXC(R11:R15,1) -> 112.995 | S21: =_xlfn.QUARTILE.EXC(S11:S15,1) -> 134.4 | T21: =_xlfn.QUARTILE.EXC(T11:T15,1) -> 52.65 | ... X21: =_xlfn.QUARTILE.EXC(X11:X15,1) -> 0.072417271
B22: Minimum | D22: =MIN(D11:D15) -> 10.86 | F22: =MIN(F11:F15) -> 364.728 | M22: =MIN(M11:M15) -> 243.728 | N22: =MIN(N11:N15) -> 749.3 | O22: =MIN(O11:O15) -> 764.3 | P22: =MIN(P11:P15) -> 806.4 | Q22: =MIN(Q11:Q15) -> 48.7 | R22: =MIN(R11:R15) -> 69.19 | S22: =MIN(S11:S15) -> 78 | T22: =MIN(T11:T15) -> 26.8 | ... X22: =MIN(X11:X15) -> 0.027289167
B24: Home Depot | C24: HD | D24: 390.13 | E24: 1002 | F24: =D24*E24 -> 390910.26 | G24: 1.01 | H24: 0.24 | I24: -1531 | J24: =44111+777 -> 44888 | K24: 0 | L24: 0 | M24: =F24+I24+J24+K24+L24 -> 434267.26 | N24: 154596 | O24: =DCF!G11 -> 154195.69 | P24: =DCF!H11 -> 158821.56 | Q24: 24984 | R24: 25191 | S24: 26089 | T24: 14610 | U24: 14792 | V24: 15453 | W24: =P24/O24-1 -> 0.03 | X24: =S24/R24-1 -> 0.035647652
G28: Capitalization | N28: EV/Rev | Q28: EV/EBITDA | T28: Equity Value/Net Income
B29: Company | C29: Ticker | F29: Market Cap | M29: EV | N29: LTM | O29: 2025E | P29: 2026E | Q29: LTM | R29: 2025E | S29: 2026E | T29: LTM | U29: 2025E | V29: 2026E
B30: Lowe's Companies | C30: LOW | F30: =F11 -> 140741.56 | M30: =M11 -> 171473.56 | N30: =IFERROR(IF(OR($M11/N11<0,$M11/N11>=100), "NM", $M11/N11), "N/A") -> 2.0481302 | O30: =IFERROR(IF(OR($M11/O11<0,$M11/O11>=100), "NM", $M11/O11), "N/A") -> 2.057765 | P30: =IFERROR(IF(OR($M11/P11<0,$M11/P11>=100), "NM", $M11/P11), "N/A") -> 2.0251985 | Q30: =IFERROR(IF(OR($M11/Q11<0,$M11/Q11>=100), "NM", $M11/Q11), "N/A") -> 13.797358 | R30: =IFERROR(IF(OR($M11/R11<0,$M11/R11>=100), "NM", $M11/R11), "N/A") -> 14.09449 | S30: =IFERROR(IF(OR($M11/S11<0,$M11/S11>=100), "NM", $M11/S11), "N/A") -> 13.72008 | T30: =IFERROR(IF(OR($F11/T11<0,$F11/T11>=100), "NM", $F11/T11), "N/A") -> 20.537219 | U30: =IFERROR(IF(OR($F11/U11<0,$F11/U11>=100), "NM", $F11/U11), "N/A") -> 20.028684 | V30: =IFERROR(IF(OR($F11/V11<0,$F11/V11>=100), "NM", $F11/V11), "N/A") -> 18.755538
B31: Builders FirstSource | C31: BLDR | F31: =F12 -> 17122.343 | M31: =M12 -> 20496.843 | N31: =IFERROR(IF(OR($M12/N12<0,$M12/N12>=100), "NM", $M12/N12), "N/A") -> 1.2250818 | O31: =IFERROR(IF(OR($M12/O12<0,$M12/O12>=100), "NM", $M12/O12), "N/A") -> 1.188912 | P31: =IFERROR(IF(OR($M12/P12<0,$M12/P12>=100), "NM", $M12/P12), "N/A") -> 1.1135957 | Q31: =IFERROR(IF(OR($M12/Q12<0,$M12/Q12>=100), "NM", $M12/Q12), "N/A") -> 8.7254025 | R31: =IFERROR(IF(OR($M12/R12<0,$M12/R12>=100), "NM", $M12/R12), "N/A") -> 8.8577541 | S31: =IFERROR(IF(OR($M12/S12<0,$M12/S12>=100), "NM", $M12/S12), "N/A") -> 7.92608 | T31: =IFERROR(IF(OR($F12/T12<0,$F12/T12>=100), "NM", $F12/T12), "N/A") -> 13.827298 | U31: =IFERROR(IF(OR($F12/U12<0,$F12/U12>=100), "NM", $F12/U12), "N/A") -> 14.993295 | V31: =IFERROR(IF(OR($F12/V12<0,$F12/V12>=100), "NM", $F12/V12), "N/A") -> 12.739839
B32: Floor & Décor | C32: FND | F32: =F13 -> 10471.527 | M32: =M13 -> 10492.127 | N32: =IFERROR(IF(OR($M13/N13<0,$M13/N13>=100), "NM", $M13/N13), "N/A") -> 2.3864726 | O32: =IFERROR(IF(OR($M13/O13<0,$M13/O13>=100), "NM", $M13/O13), "N/A") -> 2.1633252 | P32: =IFERROR(IF(OR($M13/P13<0,$M13/P13>=100), "NM", $M13/P13), "N/A") -> 1.9041973 | Q32: =IFERROR(IF(OR($M13/Q13<0,$M13/Q13>=100), "NM", $M13/Q13), "N/A") -> 22.290476 | R32: =IFERROR(IF(OR($M13/R13<0,$M13/R13>=100), "NM", $M13/R13), "N/A") -> 18.65267 | S32: =IFERROR(IF(OR($M13/S13<0,$M13/S13>=100), "NM", $M13/S13), "N/A") -> 15.673927 | T32: =IFERROR(IF(OR($F13/T13<0,$F13/T13>=100), "NM", $F13/T13), "N/A") -> 53.562798 | U32: =IFERROR(IF(OR($F13/U13<0,$F13/U13>=100), "NM", $F13/U13), "N/A") -> 49.393995 | V32: =IFERROR(IF(OR($F13/V13<0,$F13/V13>=100), "NM", $F13/V13), "N/A") -> 38.740388
B33: Arhaus Inc | C33: ARHS | F33: =F14 -> 1528.002 | M33: =M14 -> 1386.402 | N33: =IFERROR(IF(OR($M14/N14<0,$M14/N14>=100), "NM", $M14/N14), "N/A") -> 1.093377 | O33: =IFERROR(IF(OR($M14/O14<0,$M14/O14>=100), "NM", $M14/O14), "N/A") -> 1.0039117 | P33: =IFERROR(IF(OR($M14/P14<0,$M14/P14>=100), "NM", $M14/P14), "N/A") -> 0.92180984 | Q33: =IFERROR(IF(OR($M14/Q14<0,$M14/Q14>=100), "NM", $M14/Q14), "N/A") -> 8.0934151 | R33: =IFERROR(IF(OR($M14/R14<0,$M14/R14>=100), "NM", $M14/R14), "N/A") -> 8.8418495 | S33: =IFERROR(IF(OR($M14/S14<0,$M14/S14>=100), "NM", $M14/S14), "N/A") -> 7.2662579 | T33: =IFERROR(IF(OR($F14/T14<0,$F14/T14>=100), "NM", $F14/T14), "N/A") -> 19.464994 | U33: =IFERROR(IF(OR($F14/U14<0,$F14/U14>=100), "NM", $F14/U14), "N/A") -> 20.270655 | V33: =IFERROR(IF(OR($F14/V14<0,$F14/V14>=100), "NM", $F14/V14), "N/A") -> 15.564857
B34: Haverty Furniture Companies Inc | C34: HVT | F34: =F15 -> 364.728 | M34: =M15 -> 243.728 | N34: =IFERROR(IF(OR($M15/N15<0,$M15/N15>=100), "NM", $M15/N15), "N/A") -> 0.32527426 | O34: =IFERROR(IF(OR($M15/O15<0,$M15/O15>=100), "NM", $M15/O15), "N/A") -> 0.31889049 | P34: =IFERROR(IF(OR($M15/P15<0,$M15/P15>=100), "NM", $M15/P15), "N/A") -> 0.30224206 | Q34: =IFERROR(IF(OR($M15/Q15<0,$M15/Q15>=100), "NM", $M15/Q15), "N/A") -> 5.0046817 | R34: =IFERROR(IF(OR($M15/R15<0,$M15/R15>=100), "NM", $M15/R15), "N/A") -> 3.52259 | S34: =IFERROR(IF(OR($M15/S15<0,$M15/S15>=100), "NM", $M15/S15), "N/A") -> 3.1247179 | T34: =IFERROR(IF(OR($F15/T15<0,$F15/T15>=100), "NM", $F15/T15), "N/A") -> 13.609254 | U34: =IFERROR(IF(OR($F15/U15<0,$F15/U15>=100), "NM", $F15/U15), "N/A") -> 8.3328307 | V34: =IFERROR(IF(OR($F15/V15<0,$F15/V15>=100), "NM", $F15/V15), "N/A") -> 6.9938255
B36: Maximum | F36: =MAX(F30:F34) -> 140741.56 | M36: =MAX(M30:M34) -> 171473.56 | N36: =MAX(N30:N34) -> 2.3864726 | O36: =MAX(O30:O34) -> 2.1633252 | P36: =MAX(P30:P34) -> 2.0251985 | Q36: =MAX(Q30:Q34) -> 22.290476 | R36: =MAX(R30:R34) -> 18.65267 | S36: =MAX(S30:S34) -> 15.673927 | T36: =MAX(T30:T34) -> 53.562798 | ... V36: =MAX(V30:V34) -> 38.740388
B37: 75th Percentile | F37: =_xlfn.QUARTILE.EXC(F30:F34,3) -> 78931.951 | M37: =_xlfn.QUARTILE.EXC(M30:M34,3) -> 95985.201 | N37: =_xlfn.QUARTILE.EXC(N30:N34,3) -> 2.2173014 | O37: =_xlfn.QUARTILE.EXC(O30:O34,3) -> 2.1105451 | P37: =_xlfn.QUARTILE.EXC(P30:P34,3) -> 1.9646979 | Q37: =_xlfn.QUARTILE.EXC(Q30:Q34,3) -> 18.043917 | R37: =_xlfn.QUARTILE.EXC(R30:R34,3) -> 16.37358 | S37: =_xlfn.QUARTILE.EXC(S30:S34,3) -> 14.697004 | T37: =_xlfn.QUARTILE.EXC(T30:T34,3) -> 37.050008 | ... V37: =_xlfn.QUARTILE.EXC(V30:V34,3) -> 28.747963
B38: Median | F38: =MEDIAN(F30:F34) -> 10471.527 | M38: =MEDIAN(M30:M34) -> 10492.127 | N38: =MEDIAN(N30:N34) -> 1.2250818 | O38: =MEDIAN(O30:O34) -> 1.188912 | P38: =MEDIAN(P30:P34) -> 1.1135957 | Q38: =MEDIAN(Q30:Q34) -> 8.7254025 | R38: =MEDIAN(R30:R34) -> 8.8577541 | S38: =MEDIAN(S30:S34) -> 7.92608 | T38: =MEDIAN(T30:T34) -> 19.464994 | ... V38: =MEDIAN(V30:V34) -> 15.564857
B39: 25th Percentile | F39: =_xlfn.QUARTILE.EXC(F30:F34,1) -> 946.365 | M39: =_xlfn.QUARTILE.EXC(M30:M34,1) -> 815.065 | N39: =_xlfn.QUARTILE.EXC(N30:N34,1) -> 0.70932561 | O39: =_xlfn.QUARTILE.EXC(O30:O34,1) -> 0.66140107 | P39: =_xlfn.QUARTILE.EXC(P30:P34,1) -> 0.61202595 | Q39: =_xlfn.QUARTILE.EXC(Q30:Q34,1) -> 6.5490484 | R39: =_xlfn.QUARTILE.EXC(R30:R34,1) -> 6.1822197 | S39: =_xlfn.QUARTILE.EXC(S30:S34,1) -> 5.1954879 | T39: =_xlfn.QUARTILE.EXC(T30:T34,1) -> 13.718276 | ... V39: =_xlfn.QUARTILE.EXC(V30:V34,1) -> 9.866832
B40: Minimum | F40: =MIN(F30:F34) -> 364.728 | M40: =MIN(M30:M34) -> 243.728 | N40: =MIN(N30:N34) -> 0.32527426 | O40: =MIN(O30:O34) -> 0.31889049 | P40: =MIN(P30:P34) -> 0.30224206 | Q40: =MIN(Q30:Q34) -> 5.0046817 | R40: =MIN(R30:R34) -> 3.52259 | S40: =MIN(S30:S34) -> 3.1247179 | T40: =MIN(T30:T34) -> 13.609254 | ... V40: =MIN(V30:V34) -> 6.9938255
B42: Home Depot | C42: HD | F42: =F24 -> 390910.26 | M42: =M24 -> 434267.26 | N42: =IFERROR(IF(OR($M24/N24<0,$M24/N24>=100), "NM",$M24/N24), "N/A") -> 2.8090459 | O42: =IFERROR(IF(OR($M24/O24<0,$M24/O24>=100), "NM",$M24/O24), "N/A") -> 2.8163385 | P42: =IFERROR(IF(OR($M24/P24<0,$M24/P24>=100), "NM",$M24/P24), "N/A") -> 2.7343092 | Q42: =IFERROR(IF(OR($M24/Q24<0,$M24/Q24>=100), "NM",$M24/Q24), "N/A") -> 17.381815 | R42: =IFERROR(IF(OR($M24/R24<0,$M24/R24>=100), "NM",$M24/R24), "N/A") -> 17.238985 | S42: =IFERROR(IF(OR($M24/S24<0,$M24/S24>=100), "NM",$M24/S24), "N/A") -> 16.645608 | T42: =IFERROR(IF(OR($F24/T24<0,$F24/T24>=100), "NM", $F24/T24), "N/A") -> 26.756349 | U42: =IFERROR(IF(OR($F24/U24<0,$F24/U24>=100), "NM", $F24/U24), "N/A") -> 26.42714 | V42: =IFERROR(IF(OR($F24/V24<0,$F24/V24>=100), "NM", $F24/V24), "N/A") -> 25.296723

Sheet Precedents
B2: very hard to do without capIQ or Bloomberg

Sheet Charts
B2: Home Depot (NYSE: HD)
B3: Charts/Graphs
B6: Period End:
B7: USD millions (expect per share data)
B9: Revenue Growth/Revenue vs COGS vs Net Income Data
C10: FY2020A | D10: FY2021A | E10: FY2022A | F10: FY2023A | G10: FY2024E | H10: FY2025E | I10: FY2026E | J10: FY2027E | K10: FY2028E | L10: FY2029E | M10: FY2030E
B11: Revenue | C11: 132110 | D11: 151157 | E11: 157403 | F11: 152669 | G11: =F11*(1+Assumptions!G5) -> 152669 | H11: =G11*(1+Assumptions!H5) -> 152669 | I11: =H11*(1+Assumptions!I5) -> 152669 | J11: =I11*(1+Assumptions!J5) -> 152669 | K11: =J11*(1+Assumptions!K5) -> 152669 | L11: =K11*(1+Assumptions!L5) -> 152669 | M11: =L11*(1+Assumptions!M5) -> 152669
B12: Cost of Sales | C12: 87257 | D12: 100325 | E12: 104625 | F12: 101709 | G12: 102848.53 | H12: 106092.8 | I12: 109864.18 | J12: 119898.11 | K12: 124572 | L12: 129427.82 | M12: 134148.61
B13: Net Earnings (Net Income) | C13: 12866 | D13: 16433 | E13: 17105 | F13: 15143 | G13: 15201.47 | H13: 15671.39 | I13: 16229.596 | J13: 16956.706 | K13: 17603.852 | L13: 18271.431 | M13: 18912.23
B15: Revenue vs Net Income Data
C16: FY2020A | D16: FY2021A | E16: FY2022A | F16: FY2023A | G16: FY2024E | H16: FY2025E | I16: FY2026E | J16: FY2027E | K16: FY2028E | L16: FY2029E | M16: FY2030E
B17: Revenue | C17: 132110 | D17: 151157 | E17: 157403 | F17: 152669 | G17: =F17*(1+Assumptions!G13) -> 155149.8 | H17: =G17*(1+Assumptions!H13) -> 157670.91 | I17: =H17*(1+Assumptions!I13) -> 160232.98 | J17: =I17*(1+Assumptions!J13) -> 162836.69 | K17: =J17*(1+Assumptions!K13) -> 165482.71 | L17: =K17*(1+Assumptions!L13) -> 168171.72 | M17: =L17*(1+Assumptions!M13) -> 170904.43
B18: Net Earnings (Net Income) | C18: 12866 | D18: 16433 | E18: 17105 | F18: 15143 | G18: 15201.47 | H18: 15671.39 | I18: 16229.596 | J18: 16956.706 | K18: 17603.852 | L18: 18271.431 | M18: 18912.23
B20: EBITDA Growth Data
C21: FY2020A | D21: FY2021A | E21: FY2022A | F21: FY2023A | G21: FY2024E | H21: FY2025E | I21: FY2026E | J21: FY2027E | K21: FY2028E | L21: FY2029E | M21: FY2030E
B22: EBITDA | C22: 20406 | D22: 25426 | E22: 26494 | F22: 24362 | G22: 24581.389 | H22: 25160.009 | I22: 25851.228 | J22: 21653.057 | K22: 22287.34 | L22: 22938.746 | M22: 23550.779
